Workbook
Name CompsWeight: Assumptions!$B$10
Name DCFWeight: Assumptions!$B$9
Name DilutedShares: Assumptions!$B$27
Name FY2025AdjEBITDA: Assumptions!$B$24
Name MinorityInterests: Assumptions!$B$26
Name NetDebtToEBITDA: Assumptions!$B$25
Name PrimaryWACC: Assumptions!$B$7
Name SelectedScenario: Assumptions!$B$5
Name TerminalGrowth: Assumptions!$B$8

Sheet Cover
A1: SES S.A. — Company Valuation
A3: DCF & Comparable Company Analysis | Internal Investment Note
A5: TARGET | B5: SES S.A. (Euronext Paris / Luxembourg Stock Exchange) | E5: TICKER | F5: SESG
A6: PREPARED BY | B6: Joy Lorna | E6: AS OF DATE | F6: 46253
A7: ROLE / LANE | B7: Financial Analyst | Corporate Finance | Investment Analysis
A8: MODEL STATUS | B8: Educational portfolio model | Formula audit passed 19 Aug 2026 | Source-backed actuals with clearly identified illustrative market inputs
A10: PROJECT OBJECTIVE | B10: Value a European mid-cap listed company using a five-year FCFF DCF and a five-peer comparable-company analysis. The model is designed as a decision-oriented internal investment note, with a defensible fair value range, a directional view, and transparent assumptions rather than false precision.
A13: DATA INTEGRITY | B13: FY2024–FY2025 revenue and Adjusted EBITDA, FY2025 leverage, FY2026 stable outlook, the Intelsat closing date, listing details, FY2025 minority interests, and the latest economic-equivalent share count are source-based. Beta, credit spread, peer multiples, and the current market price remain market-sensitive inputs requiring refresh before any live investment decision.
A16: WORKBOOK CONTENTS
A17: Exec_Summary | B17: One-page investment memo with valuation conclusion, thesis, and risks.
A18: Assumptions | B18: Scenario control and all editable operating and valuation drivers.
A19: Data_Raw | B19: Source-backed historical inputs and source references; source rows are not edited.
A20: Historicals | B20: Clean three-year actuals, trend diagnostics, and analytical commentary.
A21: Projections | B21: Five-year operating forecast and FCFF build for FY2026E–FY2030E.
A22: WACC | B22: Bottom-up beta, CAPM cost of equity, cost of debt, and target capital structure.
A23: DCF | B23: Explicit FCFF discounting, Gordon Growth terminal value, and equity bridge.
A24: Sensitivity | B24: Two-variable enterprise-value analysis across WACC and terminal growth.
A25: Comps | B25: Five-peer EV/EBITDA and P/E framework with implied valuation ranges.
A26: Football_Field | B26: Reconciliation of DCF, comps, and blended valuation ranges.
A27: Charts | B27: Presentation-ready operating and valuation visuals.
A28: Sources | B28: Source register, URLs, and notes distinguishing sourced data from judgement.
A30: IMPORTANT — EDUCATIONAL USE ONLY. This workbook is not investment advice. Market inputs identified as illustrative must be refreshed and independently verified before use in any real investment decision.

Sheet Exec_Summary
A1: SES S.A. — Executive Investment Summary
A2: ="Internal valuation note | Selected "&Assumptions!B5&" case | Prepared by Joy Lorna | Model outputs as of 19 August 2026" -> Internal valuation note | Selected Base case | Prepared by Joy Lorna | Model outputs as of 19 August 2026
A4: INVESTMENT VIEW
A5: DIRECTIONAL VIEW | C5: BLENDED FAIR VALUE | E5: BLENDED ENTERPRISE VALUE | G5: BASE DCF VALUE
A6: ="WATCHLIST / CONDITIONAL ACCUMULATE BELOW "&TEXT(Football_Field!B36,"€0.00") -> WATCHLIST / CONDITIONAL ACCUMULATE BELOW €8.85 | C6: =TEXT(Football_Field!B36,"€0.00")&"–"&TEXT(Football_Field!C36,"€0.00")&" / share" -> €8.85–€17.51 / share | E6: ="€"&TEXT(Football_Field!B8/1000,"0.0")&"bn–€"&TEXT(Football_Field!C8/1000,"0.0")&"bn" -> €8.4bn–€12.1bn | G6: =TEXT(DCF!B14,"€0.00")&" / share" -> €16.78 / share
A10: BUSINESS SUMMARY & RECOMMENDATION RATIONALE
A11: ="SES is a Luxembourg-headquartered satellite and connectivity operator whose acquisition of Intelsat on 17 July 2025 materially changed its scale, leverage, and execution risk. The "&Assumptions!B5&" case assumes FY2026 revenue growth of "&TEXT(Projections!B7,"0.0%")&", gradual EBITDA-margin recovery from "&TEXT(Projections!B9,"0.0%")&" to "&TEXT(Projections!F9,"0.0%")&_xlfn._LONGTEXT(", and declining capital intensity. The DCF supports a higher valuation than public-market peers, while the comps framework embeds a larger discount for leverage, integration risk, structural Media pressure, and LEO competition. Accordingly, the model supp","orts a WATCHLIST / CONDITIONAL ACCUMULATE stance below the €")&TEXT(Football_Field!B36,"0.00")&" lower fair-value threshold—not an unconditional buy call—until the current share price and live peer multiples are refreshed." -> SES is a Luxembourg-headquartered satellite and connectivity operator whose acquisition of Intelsat on 17 July 2025 materially changed its scale, leverage, and execution risk. The Base case assumes FY2026 revenue growth of 0.0%, gradual EBITDA-margin recovery from 45.5% to 49.0%, and declining capital intensity. The DCF supports a higher valuation than public-market peers, while the comps framework embeds a larger discount for leverage, integration risk, structural Media pressure, and LEO competition. Accordingly, the model supports a WATCHLIST / CONDITIONAL ACCUMULATE stance below the €8.85 lower fair-value threshold—not an unconditional buy call—until the current share price and live peer multiples are refreshed.
A16: VALUATION SNAPSHOT
A17: Method | B17: Low | C17: High | D17: Interpretation
A18: DCF sensitivity | B18: =Football_Field!B6 -> 10091.447 | C18: =Football_Field!C6 -> 14116.906 | D18: Fundamentals-based range; highly sensitive to WACC and terminal growth.
A19: Comps EV / EBITDA | B19: =Football_Field!B7 -> 5976.425 | C19: =Football_Field!C7 -> 8964.6375 | D19: Public-market cross-check using illustrative 5.0x–7.5x multiples.
A20: Blended enterprise value | B20: =Football_Field!B8 -> 8445.4382 | C20: =Football_Field!C8 -> 12055.998 | D20: =TEXT(Assumptions!B9,"0%")&" DCF / "&TEXT(Assumptions!B10,"0%")&" Comps reconciliation." -> 60% DCF / 40% Comps reconciliation.
A21: Indicative value per share | B21: =Football_Field!B36 -> 8.8488805 | C21: =Football_Field!C36 -> 17.507169 | D21: Per-share range uses reported minority interests and the official economic-equivalent share count.
A22: Current market reference | B22: Not refreshed | C22: Not refreshed | D22: No validated live share price or market EV is included; recommendation remains conditional.
A24: KEY INVESTMENT FINDINGS
A25: ="1. Growth quality: Revenue increases from €"&TEXT(Projections!B6,"#,##0")&"m in FY2026E to €"&TEXT(Projections!F6,"#,##0")&"m in FY2030E, a "&TEXT((Projections!F6/Projections!B6)^(1/4)-1,"0.0%")&" CAGR." -> 1. Growth quality: Revenue increases from €2,627m in FY2026E to €2,857m in FY2030E, a 2.1% CAGR.
A26: ="2. Margin recovery: Adjusted EBITDA grows at "&TEXT((Projections!F8/Projections!B8)^(1/4)-1,"0.0%")&" CAGR as the margin recovers by "&TEXT(Projections!F9-Projections!B9,"0.0%")&" to "&TEXT(Projections!F9,"0.0%")&", still below the FY2024 standalone level." -> 2. Margin recovery: Adjusted EBITDA grows at 4.0% CAGR as the margin recovers by 3.5% to 49.0%, still below the FY2024 standalone level.
A27: ="3. Cash conversion: FCFF rises from €"&TEXT(Projections!B18,"#,##0")&"m to €"&TEXT(Projections!F18,"#,##0")&"m as CapEx intensity declines from "&TEXT(-Projections!B16/Projections!B6,"0.0%")&" to "&TEXT(-Projections!F16/Projections!F6,"0.0%")&"." -> 3. Cash conversion: FCFF rises from €366m to €748m as CapEx intensity declines from 26.4% to 16.0%.
A28: ="4. Valuation risk: Terminal value represents "&TEXT(DCF!B31,"0.0%")&" of DCF enterprise value, while the comps range remains materially below DCF; sensitivity and triangulation are therefore essential." -> 4. Valuation risk: Terminal value represents 80.0% of DCF enterprise value, while the comps range remains materially below DCF; sensitivity and triangulation are therefore essential.
A30: UPSIDE CATALYSTS | E30: DOWNSIDE RISKS
A31: • Faster Intelsat integration and synergy delivery • Sustained Government, mobility, and aviation growth • Sovereign connectivity contract wins • Deleveraging toward investment-grade metrics • Earlier CapEx normalisation and stronger cash returns | E31: • Slower deleveraging or weaker cash conversion • Accelerating Media revenue erosion • LEO constellation pricing and capacity pressure • Integration, restructuring, or execution slippage • Satellite launch, deployment, or in-orbit health risk
A37: DATA INTEGRITY & NEXT ACTION
A38: =_xlfn._LONGTEXT("Source-backed: FY2023–FY2025 revenue and Adjusted EBITDA, FY2025 leverage, FY2026 stable outlook, Intelsat closing date, listing details, reported minority interests, and economic-equivalent shares. Illustrative / refresh required: beta inputs, credit spr","ead, peer multiples, and current market price. Before using this as a live investment recommendation, refresh those market-sensitive items from Bloomberg, Capital IQ, FactSet, company filings, or broker data, then compare the validated market price with t","he €")&TEXT(Football_Field!B36,"0.00")&_xlfn.UNICHAR(8211)&"€"&TEXT(Football_Field!C36,"0.00")&" model range." -> Source-backed: FY2023–FY2025 revenue and Adjusted EBITDA, FY2025 leverage, FY2026 stable outlook, Intelsat closing date, listing details, reported minority interests, and economic-equivalent shares. Illustrative / refresh required: beta inputs, credit spread, peer multiples, and current market price. Before using this as a live investment recommendation, refresh those market-sensitive items from Bloomberg, Capital IQ, FactSet, company filings, or broker data, then compare the validated market price with the €8.85–€17.51 model range.
A43: Model conclusion: SES offers meaningful integration and cash-conversion optionality, but leverage and execution risk justify a conditional—not unconditional—positive stance.
A46: VALUATION LIMITATIONS
A47: ="• Peer multiples are snapshot market-based measures."&CHAR(10)&"• DCF is highly sensitive to WACC and terminal growth."&CHAR(10)&"• Terminal value contributes approximately "&TEXT(DCF!B31,"0%")&" of EV."&CHAR(10)&"• SES remains in a post-Intelsat integration period."&CHAR(10)&"• Valuation outputs should be interpreted as a range, not a precise estimate." -> • Peer multiples are snapshot market-based measures. • DCF is highly sensitive to WACC and terminal growth. • Terminal value contributes approximately 80% of EV. • SES remains in a post-Intelsat integration period. • Valuation outputs should be interpreted as a range, not a precise estimate.

Sheet Assumptions
A1: Assumptions & Scenario Control
A2: Central model inputs | Blue = hardcoded input • Black = formula • Green = source-linked value
A4: SCENARIO CONTROL
A5: Selected scenario | B5: Base | C5: Choose Base, Upside, or Downside; forecast and DCF inputs update automatically.
A6: Model currency | B6: EUR millions | C6: All financial statements and valuation outputs, except per-share values and multiples.
A7: Primary valuation WACC | B7: =INDEX($B$32:$B$34,MATCH($B$5,$A$32:$A$34,0)) -> 0.072 | C7: Selected-case discount rate used by the primary DCF.
A8: Terminal growth rate | B8: =INDEX($C$32:$C$34,MATCH($B$5,$A$32:$A$34,0)) -> 0.015 | C8: Selected-case long-term nominal growth rate for EUR FCFF.
A9: Blended DCF weight | B9: 0.6 | C9: Methodology weight applied to the DCF valuation range.
A10: Blended Comps weight | B10: 0.4 | C10: Methodology weight applied to the comparable-company range; weights must total 100%.
A13: SELECTED-CASE PROJECTION DRIVERS
A14: Driver | B14: FY2026E | C14: FY2027E | D14: FY2028E | E14: FY2029E | F14: FY2030E | G14: Investment rationale
A15: Revenue growth % | B15: =SUMIFS($C$39:$C$56,$A$39:$A$56,$B$5,$B$39:$B$56,$A15) -> 0 | C15: =SUMIFS($D$39:$D$56,$A$39:$A$56,$B$5,$B$39:$B$56,$A15) -> 0.015 | D15: =SUMIFS($E$39:$E$56,$A$39:$A$56,$B$5,$B$39:$B$56,$A15) -> 0.02 | E15: =SUMIFS($F$39:$F$56,$A$39:$A$56,$B$5,$B$39:$B$56,$A15) -> 0.025 | F15: =SUMIFS($G$39:$G$56,$A$39:$A$56,$B$5,$B$39:$B$56,$A15) -> 0.025 | G15: FY2026 follows management’s stable year-on-year outlook; thereafter Networks growth offsets structural Media pressure.
A16: EBITDA margin % | B16: =SUMIFS($C$39:$C$56,$A$39:$A$56,$B$5,$B$39:$B$56,$A16) -> 0.455 | C16: =SUMIFS($D$39:$D$56,$A$39:$A$56,$B$5,$B$39:$B$56,$A16) -> 0.47 | D16: =SUMIFS($E$39:$E$56,$A$39:$A$56,$B$5,$B$39:$B$56,$A16) -> 0.48 | E16: =SUMIFS($F$39:$F$56,$A$39:$A$56,$B$5,$B$39:$B$56,$A16) -> 0.485 | F16: =SUMIFS($G$39:$G$56,$A$39:$A$56,$B$5,$B$39:$B$56,$A16) -> 0.49 | G16: Base case recovers toward, but remains below, the pre-merger standalone margin because the Intelsat mix remains dilutive.
A17: D&A (% revenue) | B17: =SUMIFS($C$39:$C$56,$A$39:$A$56,$B$5,$B$39:$B$56,$A17) -> 0.26 | C17: =SUMIFS($D$39:$D$56,$A$39:$A$56,$B$5,$B$39:$B$56,$A17) -> 0.25 | D17: =SUMIFS($E$39:$E$56,$A$39:$A$56,$B$5,$B$39:$B$56,$A17) -> 0.24 | E17: =SUMIFS($F$39:$F$56,$A$39:$A$56,$B$5,$B$39:$B$56,$A17) -> 0.23 | F17: =SUMIFS($G$39:$G$56,$A$39:$A$56,$B$5,$B$39:$B$56,$A17) -> 0.225 | G17: Elevated by the satellite asset base and acquisition accounting, then tapers as the purchase-price step-up amortises.
A18: CapEx (% revenue) | B18: =SUMIFS($C$39:$C$56,$A$39:$A$56,$B$5,$B$39:$B$56,$A18) -> 0.264 | C18: =SUMIFS($D$39:$D$56,$A$39:$A$56,$B$5,$B$39:$B$56,$A18) -> 0.22 | D18: =SUMIFS($E$39:$E$56,$A$39:$A$56,$B$5,$B$39:$B$56,$A18) -> 0.19 | E18: =SUMIFS($F$39:$F$56,$A$39:$A$56,$B$5,$B$39:$B$56,$A18) -> 0.17 | F18: =SUMIFS($G$39:$G$56,$A$39:$A$56,$B$5,$B$39:$B$56,$A18) -> 0.16 | G18: FY2026 remains investment-heavy for IRIS² and meoSphere; capital intensity normalises as major build phases mature.
A19: Change in NWC (% revenue) | B19: =SUMIFS($C$39:$C$56,$A$39:$A$56,$B$5,$B$39:$B$56,$A19) -> 0.005 | C19: =SUMIFS($D$39:$D$56,$A$39:$A$56,$B$5,$B$39:$B$56,$A19) -> 0.005 | D19: =SUMIFS($E$39:$E$56,$A$39:$A$56,$B$5,$B$39:$B$56,$A19) -> 0.005 | E19: =SUMIFS($F$39:$F$56,$A$39:$A$56,$B$5,$B$39:$B$56,$A19) -> 0.005 | F19: =SUMIFS($G$39:$G$56,$A$39:$A$56,$B$5,$B$39:$B$56,$A19) -> 0.005 | G19: A modest annual cash investment is applied consistently to reflect working-capital requirements.
A20: Tax rate | B20: =SUMIFS($C$39:$C$56,$A$39:$A$56,$B$5,$B$39:$B$56,$A20) -> 0.2387 | C20: =SUMIFS($D$39:$D$56,$A$39:$A$56,$B$5,$B$39:$B$56,$A20) -> 0.2387 | D20: =SUMIFS($E$39:$E$56,$A$39:$A$56,$B$5,$B$39:$B$56,$A20) -> 0.2387 | E20: =SUMIFS($F$39:$F$56,$A$39:$A$56,$B$5,$B$39:$B$56,$A20) -> 0.2387 | F20: =SUMIFS($G$39:$G$56,$A$39:$A$56,$B$5,$B$39:$B$56,$A20) -> 0.2387 | G20: Luxembourg City’s 2025+ combined corporate rate of 23.87% is used as a simplifying proxy; SES’s group effective rate spans jurisdictions.
A23: VALUATION BRIDGE INPUTS
A24: FY2025A Adjusted EBITDA | B24: =Data_Raw!D7 -> 1196 | C24: Source-linked from SES FY2025 results via Data_Raw.
A25: Adjusted net debt / EBITDA | B25: =Data_Raw!D9 -> 3.9 | C25: Source-linked FY2025 combined like-for-like leverage.
A26: Minority interests (reported) | B26: 91 | C26: Source-based: non-controlling interests reported in SES FY2025 Annual Report at 31 December 2025.
A27: Diluted economic-equivalent shares | B27: 417.00622 | C27: Source-based: 417.006m economic-equivalent shares from SES shareholder information at 30 June 2026; fully diluted EPS is not materially different from basic EPS.
A30: VALUATION SCENARIO LIBRARY — EDIT BLUE CELLS
A31: Scenario | B31: WACC | C31: Terminal growth | D31: Case interpretation
A32: Base | B32: 0.072 | C32: 0.015 | D32: Balanced execution case: stable FY2026, gradual margin recovery, and measured deleveraging.
A33: Upside | B33: 0.067 | C33: 0.02 | D33: Faster synergy capture and lower perceived risk support stronger cash conversion and a lower discount rate.
A34: Downside | B34: 0.077 | C34: 0.01 | D34: Slower integration, persistent Media pressure, and elevated leverage increase execution risk.
A37: OPERATING SCENARIO LIBRARY — EDIT BLUE CELLS
A38: Scenario | B38: Driver | C38: FY2026E | D38: FY2027E | E38: FY2028E | F38: FY2029E | G38: FY2030E
A39: Base | B39: Revenue growth % | C39: 0 | D39: 0.015 | E39: 0.02 | F39: 0.025 | G39: 0.025
A40: Base | B40: EBITDA margin % | C40: 0.455 | D40: 0.47 | E40: 0.48 | F40: 0.485 | G40: 0.49
A41: Base | B41: D&A (% revenue) | C41: 0.26 | D41: 0.25 | E41: 0.24 | F41: 0.23 | G41: 0.225
A42: Base | B42: CapEx (% revenue) | C42: 0.264 | D42: 0.22 | E42: 0.19 | F42: 0.17 | G42: 0.16
A43: Base | B43: Change in NWC (% revenue) | C43: 0.005 | D43: 0.005 | E43: 0.005 | F43: 0.005 | G43: 0.005
A44: Base | B44: Tax rate | C44: 0.2387 | D44: 0.2387 | E44: 0.2387 | F44: 0.2387 | G44: 0.2387
A45: Upside | B45: Revenue growth % | C45: 0.005 | D45: 0.025 | E45: 0.03 | F45: 0.03 | G45: 0.03
A46: Upside | B46: EBITDA margin % | C46: 0.46 | D46: 0.48 | E46: 0.49 | F46: 0.5 | G46: 0.505
A47: Upside | B47: D&A (% revenue) | C47: 0.26 | D47: 0.248 | E47: 0.235 | F47: 0.225 | G47: 0.22
A48: Upside | B48: CapEx (% revenue) | C48: 0.255 | D48: 0.21 | E48: 0.18 | F48: 0.16 | G48: 0.15
A49: Upside | B49: Change in NWC (% revenue) | C49: 0.005 | D49: 0.005 | E49: 0.005 | F49: 0.005 | G49: 0.005
A50: Upside | B50: Tax rate | C50: 0.2387 | D50: 0.2387 | E50: 0.2387 | F50: 0.2387 | G50: 0.2387
... A56: Downside | B56: Tax rate | C56: 0.2387 | D56: 0.2387 | E56: 0.2387 | F56: 0.2387 | G56: 0.2387
A59: ASSUMPTION CLASSIFICATION
A60: Assumption | B60: Type
A61: Revenue Growth | B61: Analyst Assumption
A62: EBITDA Margin | B62: Analyst Assumption
A63: Tax Rate | B63: Source-Based
A64: WACC | B64: Market-Based
A65: Diluted Shares | B65: Source-Based
A66: Minority Interests | B66: Source-Based

Sheet Data_Raw
A1: Source Data & Provenance
A2: Controlled historical inputs | Source-backed values in green • Derived metrics in black • No illustrative valuation inputs on this tab
A4: HISTORICAL SOURCE DATA
A5: Metric | B5: FY2023A | C5: FY2024A | D5: FY2025A | E5: Unit | F5: Source document | G5: Source URL | H5: Notes | I5: Data status
A6: Revenue | B6: 2019 | C6: 2001 | D6: 2627 | E6: EURm | F6: SES FY2025 Results PDF / SES FY2024 Results Release | G6: https://www.ses.com/sites/default/files/2026-03/2603_FY2025%20Press%20Release_Final.pdf | H6: FY2025 reported revenue is €2,627m and includes Intelsat from 17 July 2025; the same official release presents FY2024 reported revenue of €2,001m. FY2023 remains the three-year comparison input. | I6: Verified against official SES sources on 19 August 2026.
A7: Adjusted EBITDA | B7: 1010 | C7: 1028 | D7: 1196 | E7: EURm | F7: SES FY2025 Results PDF / SES FY2024 Results Release | G7: https://www.ses.com/sites/default/files/2026-03/2603_FY2025%20Press%20Release_Final.pdf | H7: FY2025 reported Adjusted EBITDA is €1,196m; the same official release presents FY2024 reported Adjusted EBITDA of €1,028m. FY2023 remains the three-year comparison input. | I7: Verified against official SES sources on 19 August 2026.
A8: Adjusted EBITDA margin | B8: =B7/B6 -> 0.50024765 | C8: =C7/C6 -> 0.51374313 | D8: =D7/D6 -> 0.45527217 | E8: % | F8: Calculated from Revenue and Adjusted EBITDA | G8: n/a | H8: Live calculation; not a pasted source value. | I8: Derived
A9: Adjusted Net Debt / EBITDA | C9: 1.1 | D9: 3.9 | E9: x | F9: SES FY2025 Results / FY2024 Results | G9: https://www.ses.com/sites/default/files/2026-03/2603_FY2025%20Press%20Release_Final.pdf | H9: FY2025 combined like-for-like leverage; FY2023 is intentionally blank because no consistent model input is used. | I9: Verified against official SES sources on 19 August 2026.
A10: Adjusted Free Cash Flow | C10: 253 | D10: 229 | E10: EURm | F10: SES FY2025 Results / FY2024 Results | G10: https://www.ses.com/sites/default/files/2026-03/2603_FY2025%20Press%20Release_Final.pdf | H10: Included for context only; the valuation model uses its own FCFF construction. | I10: Verified against official SES sources on 19 August 2026.
A11: Capital Expenditure | C11: 560 | D11: 559 | E11: EURm | F11: SES FY2025 Results | G11: https://www.ses.com/sites/default/files/2026-03/2603_FY2025%20Press%20Release_Final.pdf | H11: Historical investment reference; forecast CapEx is driver-based in Assumptions. | I11: Verified against official SES sources on 19 August 2026.
A12: Completeness note: FY2023 leverage, Adjusted Free Cash Flow, and Capital Expenditure are intentionally unavailable in the controlled dataset; downstream Historicals displays these fields as n.a. rather than treating them as zero.
A14: KEY SOURCE-BACKED FACTS
A15: Fact | B15: Value | C15: Unit | D15: Effective date | E15: Source document | F15: Source URL | G15: Model use | H15: Data status | I15: Analyst note
A16: Intelsat acquisition completion | B16: Completed | C16: Event | D16: 45855 | E16: SES Intelsat Completion Release | F16: https://www.ses.com/press-release/ses-completes-acquisition-intelsat-creating-global-multi-orbit-connectivity | G16: Defines FY2025 as a transition/reporting-basis year. | H16: Source-backed | I16: Intelsat is consolidated from the closing date; FY2025 is not a clean organic-growth year.
A17: FY2026 outlook | B17: Stable year-on-year, like-for-like and constant FX | C17: Revenue outlook | D17: FY2026 | E17: SES FY2025 Results PDF | F17: https://www.ses.com/sites/default/files/2026-03/2603_FY2025%20Press%20Release_Final.pdf | G17: Anchors Base-case FY2026 revenue growth at 0.0%; the outlook applies to both Revenue and Adjusted EBITDA on a like-for-like, constant-FX basis. | H17: Source-backed | I17: The Base case follows management guidance; Upside and Downside cases deliberately test deviations from that outlook.
A18: Listing venues | B18: Euronext Paris / Luxembourg Stock Exchange | C18: Equity listing | D18: Current model basis | E18: SES shareholder information | F18: https://www.ses.com/investors/shareholder-information | G18: Confirms target identity and ticker context. | H18: Source-backed | I18: Ticker used in the cover and investment memo: SESG.
A19: Luxembourg City combined corporate tax rate | B19: 0.2387 | C19: % | D19: Tax year 2025+ | E19: PwC Luxembourg Corporate Tax Summary | F19: https://taxsummaries.pwc.com/luxembourg/corporate/taxes-on-corporate-income | G19: Simplifying tax proxy for forecast NOPAT and after-tax debt cost. | H19: Source-backed | I19: PwC reports a 23.87% combined rate for a Luxembourg City company in the top bracket: 16% corporate income tax, 1.12% solidarity surtax, and 6.75% municipal business tax. SES’s group effective rate remains multi-jurisdictional.
A23: DATA QUALITY CONTROLS
A24: Control | B24: Result | C24: Threshold / expectation | D24: Interpretation
A25: Revenue history complete | B25: =IF(COUNT(B6:D6)=3,"PASS","REVIEW") -> PASS | C25: 3 annual observations | D25: Supports the minimum three-year historical requirement.
A26: EBITDA history complete | B26: =IF(COUNT(B7:D7)=3,"PASS","REVIEW") -> PASS | C26: 3 annual observations | D26: Supports margin and growth diagnostics.
A27: Margins reconcile | B27: =IF(MAX(ABS(B8-B7/B6),ABS(C8-C7/C6),ABS(D8-D7/D6))<0.0001,"PASS","REVIEW") -> PASS | C27: Difference below 0.01 percentage points | D27: Confirms calculated margins are internally consistent.
A28: FY2025 leverage available | B28: =IF(D9>0,"PASS","REVIEW") -> PASS | C28: Positive sourced multiple | D28: Feeds the enterprise-to-equity valuation bridge.
A29: Source URLs populated | B29: =IF(COUNTIF(G6:G11,"https://*")>=5,"PASS","REVIEW") -> PASS | C29: At least five populated source rows | D29: Provides traceable source documentation inside the workbook.
A30: Primary source links verified | B30: =IF(COUNTIF(C34:C39,"Verified")=6,"PASS","REVIEW") -> PASS | C30: 6 requested official sources | D30: Confirms every requested source URL has been checked against its official live destination.
A32: VERIFIED PRIMARY SOURCE REGISTER
A33: Source | B33: Authority | C33: Verified status | D33: Verified date | E33: URL | F33: Dataset coverage | G33: Workbook use | H33: Refresh trigger | I33: Verification note
A34: SES FY2025 Results PDF | B34: SES S.A. | C34: Verified | D34: 2026-08-19T00:00:00.000Z | E34: https://www.ses.com/sites/default/files/2026-03/2603_FY2025%20Press%20Release_Final.pdf | F34: FY2025 revenue €2,627m; Adjusted EBITDA €1,196m; reported-basis consolidation from 17 July 2025; FY2026 stable outlook; leverage and CapEx context. | G34: Primary historical dataset, outlook anchor, and valuation bridge. | H34: On publication of newer full-year results. | I34: Direct official PDF resolves and matches the model’s reported figures.
A35: SES FY2024 Results Press Release | B35: SES S.A. | C35: Verified | D35: 2026-08-19T00:00:00.000Z | E35: https://www.ses.com/press-release/ses-full-year-2024-results | F35: FY2024 revenue €2,001m; Adjusted EBITDA €1,028m; net leverage 1.1x; backlog and transaction context. | G35: Historical cross-check and pre-transaction operating context. | H35: On restatement or superseding filing. | I35: Official SES release resolves and supports the FY2024 values used.
A36: SES Financial Results Hub | B36: SES S.A. | C36: Verified | D36: 2026-08-19T00:00:00.000Z | E36: https://www.ses.com/investors/financial-results | F36: Official statements, press releases, presentations, and transcripts by reporting period. | G36: Document-discovery hub and refresh workflow. | H36: At each quarterly or annual reporting event. | I36: Official hub resolves and includes FY2025, FY2024, and earlier reporting periods.
A37: SES Annual Reports | B37: SES S.A. | C37: Verified | D37: 2026-08-19T00:00:00.000Z | E37: https://www.ses.com/investors/annual-reports | F37: 2025 Annual Report, responsibility statement, official iXBRL, and report archive. | G37: Cap-table, minorities, accounting policies, and disclosure refresh. | H37: When a new annual report or filing is published. | I37: Official annual-report hub resolves and displays the 2025 Annual Report.
A38: SES Intelsat Completion Release | B38: SES S.A. | C38: Verified | D38: 2026-08-19T00:00:00.000Z | E38: https://www.ses.com/press-release/ses-completes-acquisition-intelsat-creating-global-multi-orbit-connectivity | F38: Confirms acquisition completion on 17 July 2025 and strategic transaction context. | G38: Defines the FY2025 consolidation boundary and transition-year interpretation. | H38: Only if transaction disclosures are subsequently corrected. | I38: Official SES release resolves and confirms the completion date.
A39: PwC Luxembourg Corporate Tax Summary | B39: PwC Worldwide Tax Summaries | C39: Verified | D39: 2026-08-19T00:00:00.000Z | E39: https://taxsummaries.pwc.com/luxembourg/corporate/taxes-on-corporate-income | F39: Luxembourg City combined corporate income tax rate of 23.87% for the top bracket from 2025. | G39: Forecast tax proxy and after-tax cost-of-debt calculation. | H39: When Luxembourg tax legislation or municipal rates change. | I39: Live PwC page was last reviewed 31 July 2026 and supports the 23.87% rate.

Sheet Historicals
A1: Historical Performance & Diagnostics
A2: Three-year reported performance linked to verified source data | EUR millions unless stated otherwise
A4: HISTORICAL OPERATING PERFORMANCE
A5: Metric | B5: FY2023A | C5: FY2024A | D5: FY2025A | E5: Trend diagnostic | F5: Data status | G5: Analyst interpretation
A6: Revenue | B6: =Data_Raw!B6 -> 2019 | C6: =Data_Raw!C6 -> 2001 | D6: =Data_Raw!D6 -> 2627 | E6: =(D6/B6)^(1/2)-1 -> 0.14067488 | F6: =IF(Data_Raw!I6="Derived","Calculated","Source-linked") -> Source-linked | G6: Reported revenue increased sharply in FY2025, but the acquisition-driven consolidation means this is not comparable organic growth.
A7: Adjusted EBITDA | B7: =Data_Raw!B7 -> 1010 | C7: =Data_Raw!C7 -> 1028 | D7: =Data_Raw!D7 -> 1196 | E7: =(D7/B7)^(1/2)-1 -> 0.088190432 | F7: =IF(Data_Raw!I7="Derived","Calculated","Source-linked") -> Source-linked | G7: Reported EBITDA increased less quickly than revenue, indicating material dilution in the combined-company margin.
A8: Adjusted EBITDA margin | B8: =Data_Raw!B8 -> 0.50024765 | C8: =Data_Raw!C8 -> 0.51374313 | D8: =Data_Raw!D8 -> 0.45527217 | E8: =(D8-C8)*100 -> -5.8470955 | F8: =IF(Data_Raw!I8="Derived","Calculated","Source-linked") -> Calculated | G8: The FY2025 margin reset is the central operating debate; the forecast assumes gradual recovery rather than an immediate return to 51%+.
A9: Adjusted Net Debt / EBITDA | B9: =IF(Data_Raw!B9="","n.a.",Data_Raw!B9) -> n.a. | C9: =IF(Data_Raw!C9="","n.a.",Data_Raw!C9) -> 1.1 | D9: =IF(Data_Raw!D9="","n.a.",Data_Raw!D9) -> 3.9 | E9: =D9-C9 -> 2.8 | F9: =IF(Data_Raw!I9="Derived","Calculated","Source-linked") -> Source-linked | G9: Leverage rose after the Intelsat transaction; valuation therefore uses a target capital structure and explicitly highlights deleveraging risk.
A10: Adjusted Free Cash Flow | B10: =IF(Data_Raw!B10="","n.a.",Data_Raw!B10) -> n.a. | C10: =IF(Data_Raw!C10="","n.a.",Data_Raw!C10) -> 253 | D10: =IF(Data_Raw!D10="","n.a.",Data_Raw!D10) -> 229 | E10: =D10/C10-1 -> -0.09486166 | F10: =IF(Data_Raw!I10="Derived","Calculated","Source-linked") -> Source-linked | G10: Adjusted FCF declined year-on-year despite higher reported EBITDA, underscoring integration and investment demands.
A11: Capital Expenditure | B11: =IF(Data_Raw!B11="","n.a.",Data_Raw!B11) -> n.a. | C11: =IF(Data_Raw!C11="","n.a.",Data_Raw!C11) -> 560 | D11: =IF(Data_Raw!D11="","n.a.",Data_Raw!D11) -> 559 | E11: =D11/C11-1 -> -0.0017857143 | F11: =IF(Data_Raw!I11="Derived","Calculated","Source-linked") -> Source-linked | G11: Capital expenditure remained broadly flat at an elevated level, consistent with a capital-intensive satellite infrastructure model.
A14: KEY HISTORICAL DIAGNOSTICS
A15: Reported revenue growth | C15: =D6/C6-1 -> 0.31284358 | E15: FY2025 versus FY2024, reported basis; acquisition consolidation is the main driver.
A16: Reported EBITDA growth | C16: =D7/C7-1 -> 0.16342412 | E16: FY2025 versus FY2024, reported basis; growth lagged revenue as the blended margin compressed.
A17: EBITDA margin change | C17: =(D8-C8)*100 -> -5.8470955 | E17: FY2025 versus FY2024; the decline captures mix dilution and transition effects.
A18: Leverage change | C18: =D9-C9 -> 2.8 | E18: FY2025 versus FY2024; the post-transaction balance sheet carries materially greater financial risk.
A21: STORY IN BRIEF
A22: ="FY2025 marks a structural break rather than a normal trend year. Reported revenue rose "&TEXT(C15,"0.0%")&" and Adjusted EBITDA rose "&TEXT(C16,"0.0%")&" versus FY2024, primarily because Intelsat was consolidated from 17 July 2025. However, the EBITDA margin fell by "&TEXT(ABS(C17),"0.0")&" percentage points to "&TEXT(D8,"0.0%")&", while leverage increased by "&TEXT(C18,"0.0x")&" to "&TEXT(D9,"0.0x")&". The model therefore treats FY2025 as the combined-company launch point and makes margin recovery, cash conversion, and deleveraging the core valuation tests." -> FY2025 marks a structural break rather than a normal trend year. Reported revenue rose 31.3% and Adjusted EBITDA rose 16.3% versus FY2024, primarily because Intelsat was consolidated from 17 July 2025. However, the EBITDA margin fell by 5.8 percentage points to 45.5%, while leverage increased by 2.8x to 3.9x. The model therefore treats FY2025 as the combined-company launch point and makes margin recovery, cash conversion, and deleveraging the core valuation tests.
A27: MODELLING IMPLICATION
A28: Do not extrapolate the FY2023–FY2025 reported revenue CAGR as an organic run rate. The forecast instead begins with management’s stable FY2026 outlook, assumes a gradual recovery in EBITDA margin, and retains explicit sensitivity to discount-rate and terminal-growth uncertainty.

Sheet Projections
A1: Five-Year Operating Projection
A2: Selected-case forecast | FY2026E–FY2030E | Live drivers from Assumptions | EUR millions unless stated otherwise
A4: FORECAST INCOME STATEMENT & FCFF BUILD
A5: Metric | B5: FY2026E | C5: FY2027E | D5: FY2028E | E5: FY2029E | F5: FY2030E | G5: Formula logic / valuation relevance
A6: Revenue | B6: =Data_Raw!D6*(1+Assumptions!B15) -> 2627 | C6: =B6*(1+Assumptions!C15) -> 2666.405 | D6: =C6*(1+Assumptions!D15) -> 2719.7331 | E6: =D6*(1+Assumptions!E15) -> 2787.7264 | F6: =E6*(1+Assumptions!F15) -> 2857.4196 | G6: Prior-year revenue × (1 + selected-case growth). FY2026 begins from FY2025 reported revenue.
A7: Revenue growth | B7: =Assumptions!B15 -> 0 | C7: =Assumptions!C15 -> 0.015 | D7: =Assumptions!D15 -> 0.02 | E7: =Assumptions!E15 -> 0.025 | F7: =Assumptions!F15 -> 0.025 | G7: Scenario-selected growth; Base case starts at 0.0% in line with management’s stable FY2026 outlook.
A8: Adjusted EBITDA | B8: =B6*Assumptions!B16 -> 1195.285 | C8: =C6*Assumptions!C16 -> 1253.2103 | D8: =D6*Assumptions!D16 -> 1305.4719 | E8: =E6*Assumptions!E16 -> 1352.0473 | F8: =F6*Assumptions!F16 -> 1400.1356 | G8: Revenue × selected-case EBITDA margin.
A9: EBITDA margin | B9: =Assumptions!B16 -> 0.455 | C9: =Assumptions!C16 -> 0.47 | D9: =Assumptions!D16 -> 0.48 | E9: =Assumptions!E16 -> 0.485 | F9: =Assumptions!F16 -> 0.49 | G9: Gradual recovery tests Intelsat integration and synergy delivery.
A10: D&A | B10: =-B6*Assumptions!B17 -> -683.02 | C10: =-C6*Assumptions!C17 -> -666.60125 | D10: =-D6*Assumptions!D17 -> -652.73594 | E10: =-E6*Assumptions!E17 -> -641.17708 | F10: =-F6*Assumptions!F17 -> -642.91941 | G10: Revenue × D&A assumption; shown as a deduction above EBIT.
A11: D&A as % of revenue | B11: =Assumptions!B17 -> 0.26 | C11: =Assumptions!C17 -> 0.25 | D11: =Assumptions!D17 -> 0.24 | E11: =Assumptions!E17 -> 0.23 | F11: =Assumptions!F17 -> 0.225 | G11: Purchase-price accounting and satellite depreciation taper gradually.
A12: EBIT | B12: =B8+B10 -> 512.265 | C12: =C8+C10 -> 586.6091 | D12: =D8+D10 -> 652.73594 | E12: =E8+E10 -> 710.87024 | F12: =F8+F10 -> 757.21619 | G12: Adjusted EBITDA less D&A.
A13: Tax on EBIT | B13: =-B12*Assumptions!B20 -> -122.27766 | C13: =-C12*Assumptions!C20 -> -140.02359 | D13: =-D12*Assumptions!D20 -> -155.80807 | E13: =-E12*Assumptions!E20 -> -169.68473 | F13: =-F12*Assumptions!F20 -> -180.7475 | G13: EBIT × Luxembourg tax proxy; actual group tax spans jurisdictions.
A14: NOPAT | B14: =B12+B13 -> 389.98734 | C14: =C12+C13 -> 446.58551 | D14: =D12+D13 -> 496.92787 | E14: =E12+E13 -> 541.18551 | F14: =F12+F13 -> 576.46869 | G14: After-tax operating profit available before reinvestment.
A15: Add: D&A | B15: =-B10 -> 683.02 | C15: =-C10 -> 666.60125 | D15: =-D10 -> 652.73594 | E15: =-E10 -> 641.17708 | F15: =-F10 -> 642.91941 | G15: Non-cash D&A is added back in the FCFF bridge.
A16: Less: Capital expenditure | B16: =-B6*Assumptions!B18 -> -693.528 | C16: =-C6*Assumptions!C18 -> -586.6091 | D16: =-D6*Assumptions!D18 -> -516.74929 | E16: =-E6*Assumptions!E18 -> -473.91349 | F16: =-F6*Assumptions!F18 -> -457.18713 | G16: Capital-intensive reinvestment; major build activity normalises over time.
A17: Less: Change in NWC | B17: =-B6*Assumptions!B19 -> -13.135 | C17: =-C6*Assumptions!C19 -> -13.332025 | D17: =-D6*Assumptions!D19 -> -13.598665 | E17: =-E6*Assumptions!E19 -> -13.938632 | F17: =-F6*Assumptions!F19 -> -14.287098 | G17: Modest working-capital investment linked to revenue.
A18: FCFF | B18: =B14+B15+B16+B17 -> 366.34434 | C18: =C14+C15+C16+C17 -> 513.24563 | D18: =D14+D15+D16+D17 -> 619.31586 | E18: =E14+E15+E16+E17 -> 694.51047 | F18: =F14+F15+F16+F17 -> 747.91386 | G18: Unlevered cash flow discounted in the DCF and used for terminal value.
A21: FORECAST DIAGNOSTICS
A22: Metric | B22: FY2026E | C22: FY2030E | D22: Change / CAGR
A23: Revenue | B23: =B6 -> 2627 | C23: =F6 -> 2857.4196 | D23: =(C23/B23)^(1/4)-1 -> 0.021241574 | E23: Low-single-digit revenue growth reflects a mature infrastructure profile rather than a high-growth case.
A24: Adjusted EBITDA | B24: =B8 -> 1195.285 | C24: =F8 -> 1400.1356 | D24: =(C24/B24)^(1/4)-1 -> 0.040338467 | E24: EBITDA growth outpaces revenue as the model assumes integration benefits and operating leverage.
A25: EBITDA margin | B25: =B9 -> 0.455 | C25: =F9 -> 0.49 | D25: =(C25-B25)*100 -> 3.5 | E25: Margin recovery is meaningful but remains below the 51.4% FY2024 standalone level.
A26: FCFF | B26: =B18 -> 366.34434 | C26: =F18 -> 747.91386 | D26: =(C26/B26)^(1/4)-1 -> 0.19533744 | E26: FCFF scales materially as margins recover and capital intensity normalises.
A27: FCFF margin | B27: =B18/B6 -> 0.1394535 | C27: =F18/F6 -> 0.2617445 | D27: =(C27-B27)*100 -> 12.2291 | E27: Cash conversion improves, reducing dependence on terminal-value assumptions over time.
A28: Capital expenditure / revenue | B28: =-B16/B6 -> 0.264 | C28: =-F16/F6 -> 0.16 | D28: =(C28-B28)*100 -> -10.4 | E28: CapEx intensity declines as IRIS², meoSphere, and major fleet investment phases mature.
A30: FORECAST STORY IN BRIEF
A31: ="The "&Assumptions!B5&" case holds FY2026 revenue at €"&TEXT(B6,"#,##0")&"m before growth resumes, reaching €"&TEXT(F6,"#,##0")&"m by FY2030. EBITDA margin expands from "&TEXT(B9,"0.0%")&" to "&TEXT(F9,"0.0%")&", while CapEx intensity falls from "&TEXT(-B16/B6,"0.0%")&" to "&TEXT(-F16/F6,"0.0%")&". These changes lift FCFF from €"&TEXT(B18,"#,##0")&"m to €"&TEXT(F18,"#,##0")&"m. The valuation therefore depends less on top-line acceleration than on disciplined integration, margin recovery, and capital normalisation." -> The Base case holds FY2026 revenue at €2,627m before growth resumes, reaching €2,857m by FY2030. EBITDA margin expands from 45.5% to 49.0%, while CapEx intensity falls from 26.4% to 16.0%. These changes lift FCFF from €366m to €748m. The valuation therefore depends less on top-line acceleration than on disciplined integration, margin recovery, and capital normalisation.
A36: MODEL INTEGRITY CHECKS
A37: Check | B37: Result | C37: Expectation
A38: Scenario drivers linked | B38: =IF(AND(B7=Assumptions!B15,C7=Assumptions!C15,D7=Assumptions!D15,E7=Assumptions!E15,F7=Assumptions!F15),"PASS","REVIEW") -> PASS | C38: All five annual drivers match the selected scenario.
A39: FCFF bridge balances | B39: =IF(MAX(ABS(B18-SUM(B14:B17)),ABS(C18-SUM(C14:C17)),ABS(D18-SUM(D14:D17)),ABS(E18-SUM(E14:E17)),ABS(F18-SUM(F14:F17)))<0.01,"PASS","REVIEW") -> PASS | C39: FCFF equals NOPAT + D&A − CapEx − change in NWC.
A40: Forecast periods complete | B40: =IF(COUNT(B6:F18)=65,"PASS","REVIEW") -> PASS | C40: All 65 numeric forecast cells are populated.
A41: Terminal-year WACC spread positive | B41: =IF(Assumptions!B7>Assumptions!B8,"PASS","REVIEW") -> PASS | C41: WACC must exceed terminal growth for a valid Gordon Growth calculation.

Sheet WACC
A1: Weighted Average Cost of Capital
A2: Bottom-up beta and target-capital-structure approach | Refreshable market inputs are explicitly identified
A3: Market Data Observation Date | B3: =DATE(2026,8,19) -> 46253 | C3: All market-sensitive inputs must be aligned to this observation date; less-frequent published series use the latest available data as of that date.
A4: COST OF EQUITY — CAPM PLUS EXECUTION-RISK PREMIUM
A5: Risk-free rate — German Bund reference proxy (Aug-2032 maturity) | B5: 0.0299 | C5: Market-based EUR input as of 18 August 2026: 2.99% yield on the 1.70% German Federal bond maturing 15 August 2032 (ISIN DE0001102606). This is a liquid Bund reference proxy with approximately six years remaining, not a constant-maturity 10-year yield. Deutsche Bundesbank reference-price data via Deutsche Finanzagentur.
A6: Mature-market equity risk premium | B6: 0.0423 | C6: Market-based mature-market proxy: Damodaran’s 4.23% implied equity risk premium, January 2026 update.
A7: Company-specific risk premium | B7: 0.01 | C7: Analyst judgement for Intelsat integration, cash conversion, and deleveraging execution risk.
A8: Target Debt / Value | B8: 0.35 | C8: Target structure used for valuation; avoids mechanically capitalising temporary post-transaction leverage.
A9: Target Equity / Value | B9: =1-B8 -> 0.65 | C9: Formula: 1 − target Debt / Value.
A10: Tax rate | B10: 0.2387 | C10: Source-linked Luxembourg City top-bracket proxy; SES’s effective rate spans several jurisdictions.
A13: BOTTOM-UP BETA
A14: Peer | B14: Levered beta | C14: Debt / Equity | D14: Tax rate | E14: Unlevered beta | F14: Input status | G14: Refresh note
A15: Eutelsat Communications | B15: 1.15 | C15: 0.85 | D15: 0.25 | E15: =B15/(1+(1-D15)*C15) -> 0.70229008 | F15: Illustrative | G15: Refresh beta, market equity, debt, and marginal tax rate from Bloomberg, Capital IQ, FactSet, or current filings.
A16: Iridium Communications | B16: 0.95 | C16: 0.15 | D16: 0.21 | E16: =B16/(1+(1-D16)*C16) -> 0.84935181 | F16: Illustrative | G16: Refresh beta, market equity, debt, and marginal tax rate from Bloomberg, Capital IQ, FactSet, or current filings.
A17: Viasat Inc. | B17: 1.3 | C17: 1.2 | D17: 0.21 | E17: =B17/(1+(1-D17)*C17) -> 0.66735113 | F17: Illustrative | G17: Refresh beta, market equity, debt, and marginal tax rate from Bloomberg, Capital IQ, FactSet, or current filings.
A18: Telesat Corporation | B18: 1.4 | C18: 2 | D18: 0.265 | E18: =B18/(1+(1-D18)*C18) -> 0.56680162 | F18: Illustrative | G18: Refresh beta, market equity, debt, and marginal tax rate from Bloomberg, Capital IQ, FactSet, or current filings.
A19: EchoStar Corporation | B19: 1.05 | C19: 0.9 | D19: 0.21 | E19: =B19/(1+(1-D19)*C19) -> 0.61367621 | F19: Illustrative | G19: Refresh beta, market equity, debt, and marginal tax rate from Bloomberg, Capital IQ, FactSet, or current filings.
A21: Average unlevered beta | E21: =AVERAGE(E15:E19) -> 0.67989417 | F21: Formula
A22: Target Debt / Equity | E22: =B8/B9 -> 0.53846154 | F22: Formula
A23: Relevered beta | E23: =E21*(1+(1-B10)*E22) -> 0.95860371 | F23: Formula
A24: Cost of equity | E24: =B5+E23*B6+B7 -> 0.080448937 | F24: Formula
A26: COST OF DEBT & WACC RECONCILIATION
A27: Pre-tax cost of debt | B27: 0.043 | C27: Illustrative debt-cost input. Refresh using SES’s observable EUR bond yields / credit spread and current debt mix.
A28: After-tax cost of debt | B28: =B27*(1-B10) -> 0.0327359 | C28: Formula: pre-tax cost of debt × (1 − tax rate).
A29: Calculated WACC | B29: =B9*E24+B8*B28 -> 0.063749374 | C29: Formula: Equity / Value × cost of equity + Debt / Value × after-tax cost of debt.
A30: Primary valuation WACC used in DCF | B30: =Assumptions!B7 -> 0.072 | C30: Selected scenario WACC. The Base case rounds above the mechanical calculation to reflect input uncertainty.
A33: WEIGHTED COMPONENT BRIDGE
A34: Equity weight | B34: =B9 -> 0.65 | C34: ="Equity contribution to WACC: "&TEXT(B34*B35,"0.00%") -> Equity contribution to WACC: 5.23%
A35: Cost of equity | B35: =E24 -> 0.080448937 | C35: CAPM plus company-specific risk premium.
A36: Debt weight | B36: =B8 -> 0.35 | C36: ="Debt contribution to WACC: "&TEXT(B36*B37,"0.00%") -> Debt contribution to WACC: 1.15%
A37: After-tax cost of debt | B37: =B28 -> 0.0327359 | C37: Tax shield applied to the illustrative pre-tax debt cost.
A39: METHODOLOGY & INVESTMENT INTERPRETATION
A40: Bottom-up beta | C40: Peer levered betas are unlevered using each peer’s D/E and tax rate, averaged, then relevered to SES’s target D/E.
A41: Target capital structure | C41: A 35% debt / 65% equity target reflects a normalised valuation structure rather than the temporary post-acquisition balance sheet.
A42: Selected WACC | C42: The primary 7.2% Base-case WACC is 0.8 percentage points above the refreshed mechanical result, providing a conservative buffer for beta, credit-spread, integration, and capital-structure uncertainty.
A43: Key limitation | C43: The risk-free rate and ERP are now source-based snapshots, but peer betas, D/E ratios, company-specific premium, and pre-tax debt cost remain refreshable modelling inputs.
A46: MODEL INTEGRITY & REFRESH CONTROLS
A47: Control | B47: Result | C47: Expectation
A48: Capital weights sum to 100% | B48: =IF(ABS(B8+B9-1)<0.0001,"PASS","REVIEW") -> PASS | C48: Debt / Value plus Equity / Value equals 100%. | E48: Input classification | F48: As-of / status | G48: Source
A49: Peer beta formulas complete | B49: =IF(COUNT(E15:E19)=5,"PASS","REVIEW") -> PASS | C49: All five peer unlevered betas calculate numerically. | E49: Risk-free rate | F49: 46252 | G49: German Federal bond / Bundesbank reference data
A50: After-tax debt cost valid | B50: =IF(AND(B28>0,B28<B27),"PASS","REVIEW") -> PASS | C50: After-tax debt cost is positive and below pre-tax cost. | E50: Equity risk premium | F50: 46023 | G50: Damodaran implied ERP
A51: Primary WACC exceeds terminal growth | B51: =IF(B30>Assumptions!B8,"PASS","REVIEW") -> PASS | C51: Required for a valid Gordon Growth terminal value. | E51: Peer beta set | F51: Illustrative | G51: Refresh from approved market-data platform
A52: Primary WACC within sensitivity range | B52: =IF(AND(B30>=Sensitivity!A6,B30<=Sensitivity!A10),"PASS","REVIEW") -> PASS | C52: Selected WACC lies inside the ±1.0 percentage-point sensitivity range. | E52: Pre-tax cost of debt | F52: Illustrative | G52: Refresh from SES observable debt yields
A53: Market inputs dated and sourced | B53: =IF(AND(B5=2.99%,B6=4.23%),"PASS","REVIEW") -> PASS | C53: Risk-free rate and ERP match the documented market snapshots. | G53: Market-data control
A55: REFRESH REFERENCES
A56: ECB euro-area yield curves — secondary cross-check | B56: https://www.ecb.europa.eu/stats/financial_markets_and_interest_rates/euro_area_yield_curves/html/index.en.html
A57: Deutsche Finanzagentur bond factsheet — exact risk-free proxy | B57: https://www.deutsche-finanzagentur.de/en/federal-securities/factsheet/isin/DE0001102606
A58: Damodaran historical implied ERP — January 2026 annual update | B58: https://pages.stern.nyu.edu/~adamodar/New_Home_Page/datafile/histimpl.html
A59: SES debtholder information — debt-cost refresh reference | B59: https://www.ses.com/investors/debtholder-information

Sheet DCF
A1: Discounted Cash Flow Valuation
A2: FCFF-based enterprise valuation | Gordon Growth terminal value | Selected-case assumptions | EUR millions unless stated otherwise
A4: DCF OUTPUT SUMMARY
A5: WACC | B5: =Assumptions!B7 -> 0.072 | C5: Selected scenario discount rate from Assumptions.
A6: Terminal growth | B6: =Assumptions!B8 -> 0.015 | C6: Selected scenario long-term nominal FCFF growth rate.
A7: PV of explicit FCFF | B7: =SUM(B23:F23) -> 2345.2707 | C7: Present value of FY2026E–FY2030E FCFF.
A8: PV of terminal value | B8: =B30 -> 9407.3834 | C8: Present value of the Gordon Growth terminal value.
A9: Enterprise value | B9: =B7+B8 -> 11752.654 | C9: Enterprise value before net debt and minority interests.
A10: Less: Adjusted net debt | B10: =Assumptions!B24*Assumptions!B25 -> 4664.4 | C10: FY2025 leverage × FY2025 Adjusted EBITDA; source-linked inputs.
A11: Less: Minority interests | B11: =Assumptions!B26 -> 91 | C11: FY2025 reported non-controlling interests from the SES Annual Report.
A12: Equity value | B12: =B9-B10-B11 -> 6997.254 | C12: Enterprise value less adjusted net debt and reported minority interests.
A13: Diluted economic-equivalent shares | B13: =Assumptions!B27 -> 417.00622 | C13: Official SES economic-equivalent share count at 30 June 2026; fully diluted EPS is not materially different from basic EPS.
A14: Implied value per share | B14: =B12/B13 -> 16.779735 | C14: Indicative value per A-share/FDR using the source-based economic-equivalent share count.
A15: ENTERPRISE VALUE → EQUITY VALUE BRIDGE
A16: Enterprise Value | B16: Less: Net Debt | C16: Less: Minorities | D16: Equity Value
A17: =B9 -> 11752.654 | B17: =-B10 -> -4664.4 | C17: =-B11 -> -91 | D17: =B12 -> 6997.254
A18: Source-based equity bridge: FY2025 reported non-controlling interests and the latest official economic-equivalent share count are used.
A19: DISCOUNTED FCFF FORECAST
A20: Metric | B20: FY2026E | C20: FY2027E | D20: FY2028E | E20: FY2029E | F20: FY2030E | G20: Formula logic
A21: FCFF | B21: =Projections!B18 -> 366.34434 | C21: =Projections!C18 -> 513.24563 | D21: =Projections!D18 -> 619.31586 | E21: =Projections!E18 -> 694.51047 | F21: =Projections!F18 -> 747.91386 | G21: Linked from the selected-case projection.
A22: Discount factor | B22: =1/(1+$B$5)^1 -> 0.93283582 | C22: =1/(1+$B$5)^2 -> 0.87018267 | D22: =1/(1+$B$5)^3 -> 0.81173756 | E22: =1/(1+$B$5)^4 -> 0.75721788 | F22: =1/(1+$B$5)^5 -> 0.70635996 | G22: 1 ÷ (1 + WACC)^year.
A23: PV of FCFF | B23: =B21*B22 -> 341.73913 | C23: =C21*C22 -> 446.61745 | D23: =D21*D22 -> 502.72195 | E23: =E21*E22 -> 525.89574 | F23: =F21*F22 -> 528.29641 | G23: FCFF × discount factor.
A26: TERMINAL VALUE
A27: Terminal FCFF | B27: =F21*(1+$B$6) -> 759.13257 | C27: FY2030 FCFF × (1 + terminal growth).
A28: Terminal value at FY2030 | B28: =B27/($B$5-$B$6) -> 13318.115 | C28: Terminal FCFF ÷ (WACC − terminal growth).
A29: Terminal discount factor | B29: =F22 -> 0.70635996 | C29: FY2030 discount factor, carried from the explicit forecast.
A30: PV of terminal value | B30: =B28*B29 -> 9407.3834 | C30: Terminal value × terminal discount factor.
A31: Terminal value as % of EV | B31: =B30/B9 -> 0.80044757 | C31: Measures dependence on cash flows beyond the explicit forecast period.
A34: VALUATION DIAGNOSTICS
A35: Diagnostic | B35: Value | C35: Interpretation
A36: Explicit FCFF contribution | B36: =B7/B9 -> 0.19955243 | C36: Only the first five forecast years; the remaining value is captured in the terminal period.
A37: Terminal value contribution | B37: =B8/B9 -> 0.80044757 | C37: High, but consistent with a long-duration, low-growth infrastructure asset; sensitivity is therefore essential.
A38: Net debt and minorities / EV | B38: =(B10+B11)/B9 -> 0.4046235 | C38: Shows how post-transaction leverage materially reduces enterprise value available to equity holders.
A39: WACC less terminal growth | B39: =B5-B6 -> 0.057 | C39: A positive spread is required for the Gordon Growth formula; smaller spreads increase valuation sensitivity.
A41: VALUATION STORY IN BRIEF
A42: ="The "&Assumptions!B5&"-case DCF values SES at €"&TEXT(B9/1000,"0.0")&"bn of enterprise value and €"&TEXT(B12/1000,"0.0")&"bn of equity value. The source-based indicative per-share value is €"&TEXT(B14,"0.00")&". Terminal value contributes "&TEXT(B31,"0%")&" of enterprise value, so the result is highly sensitive to the "&TEXT(B5,"0.0%")&" WACC and "&TEXT(B6,"0.0%")&" terminal-growth assumptions. Adjusted net debt and minorities absorb "&TEXT((B10+B11)/B9,"0%")&" of enterprise value, making deleveraging a central equity-value catalyst." -> The Base-case DCF values SES at €11.8bn of enterprise value and €7.0bn of equity value. The source-based indicative per-share value is €16.78. Terminal value contributes 80% of enterprise value, so the result is highly sensitive to the 7.2% WACC and 1.5% terminal-growth assumptions. Adjusted net debt and minorities absorb 40% of enterprise value, making deleveraging a central equity-value catalyst.
A47: MODEL INTEGRITY & JUDGEMENT CONTROLS
A48: Control | B48: Result | C48: Expectation
A49: WACC exceeds terminal growth | B49: =IF(B5>B6,"PASS","REVIEW") -> PASS | C49: Required for a mathematically valid Gordon Growth terminal value.
A50: Explicit FCFF links complete | B50: =IF(COUNT(B21:F21)=5,"PASS","REVIEW") -> PASS | C50: Five years of FCFF are linked from Projections.
A51: Enterprise value bridge balances | B51: =IF(ABS(B9-B7-B8)<0.01,"PASS","REVIEW") -> PASS | C51: Enterprise value equals explicit-period PV plus terminal-value PV.
A52: Equity bridge balances | B52: =IF(ABS(B12-(B9-B10-B11))<0.01,"PASS","REVIEW") -> PASS | C52: Equity value equals enterprise value less net debt and minorities.
A53: Terminal value share reasonable | B53: =IF(B31<=85%,"PASS","REVIEW") -> PASS | C53: The model flags terminal value above 85% of EV for heightened review.
A54: Per-share value uses positive share count | B54: =IF(B13>0,"PASS","REVIEW") -> PASS | C54: Prevents division by zero and confirms a usable equity bridge.

Sheet Sensitivity
A1: DCF Sensitivity Analysis
A2: Two-variable analysis of WACC and terminal growth | Enterprise value and indicative equity value per share
A4: ENTERPRISE VALUE SENSITIVITY (€m)
A5: WACC Terminal growth | B5: 0.005 | C5: 0.01 | D5: 0.015 | E5: 0.02 | F5: 0.025 | G5: WACC interpretation
A6: 0.062 | B6: =SUM(Projections!B18/(1+$A6)^1,Projections!C18/(1+$A6)^2,Projections!D18/(1+$A6)^3,Projections!E18/(1+$A6)^4,Projections!F18/(1+$A6)^5)+(Projections!F18*(1+B$5)/($A6-B$5))/(1+$A6)^5 -> 12178.291 | C6: =SUM(Projections!B18/(1+$A6)^1,Projections!C18/(1+$A6)^2,Projections!D18/(1+$A6)^3,Projections!E18/(1+$A6)^4,Projections!F18/(1+$A6)^5)+(Projections!F18*(1+C$5)/($A6-C$5))/(1+$A6)^5 -> 13170.14 | D6: =SUM(Projections!B18/(1+$A6)^1,Projections!C18/(1+$A6)^2,Projections!D18/(1+$A6)^3,Projections!E18/(1+$A6)^4,Projections!F18/(1+$A6)^5)+(Projections!F18*(1+D$5)/($A6-D$5))/(1+$A6)^5 -> 14373.02 | E6: =SUM(Projections!B18/(1+$A6)^1,Projections!C18/(1+$A6)^2,Projections!D18/(1+$A6)^3,Projections!E18/(1+$A6)^4,Projections!F18/(1+$A6)^5)+(Projections!F18*(1+E$5)/($A6-E$5))/(1+$A6)^5 -> 15862.3 | F6: =SUM(Projections!B18/(1+$A6)^1,Projections!C18/(1+$A6)^2,Projections!D18/(1+$A6)^3,Projections!E18/(1+$A6)^4,Projections!F18/(1+$A6)^5)+(Projections!F18*(1+F$5)/($A6-F$5))/(1+$A6)^5 -> 17754.088 | G6: 6.2%: low discount-rate case; values are most exposed to terminal-growth optimism.
A7: 0.067 | B7: =SUM(Projections!B18/(1+$A7)^1,Projections!C18/(1+$A7)^2,Projections!D18/(1+$A7)^3,Projections!E18/(1+$A7)^4,Projections!F18/(1+$A7)^5)+(Projections!F18*(1+B$5)/($A7-B$5))/(1+$A7)^5 -> 11146.638 | C7: =SUM(Projections!B18/(1+$A7)^1,Projections!C18/(1+$A7)^2,Projections!D18/(1+$A7)^3,Projections!E18/(1+$A7)^4,Projections!F18/(1+$A7)^5)+(Projections!F18*(1+C$5)/($A7-C$5))/(1+$A7)^5 -> 11963.027 | D7: =SUM(Projections!B18/(1+$A7)^1,Projections!C18/(1+$A7)^2,Projections!D18/(1+$A7)^3,Projections!E18/(1+$A7)^4,Projections!F18/(1+$A7)^5)+(Projections!F18*(1+D$5)/($A7-D$5))/(1+$A7)^5 -> 12936.415 | E7: =SUM(Projections!B18/(1+$A7)^1,Projections!C18/(1+$A7)^2,Projections!D18/(1+$A7)^3,Projections!E18/(1+$A7)^4,Projections!F18/(1+$A7)^5)+(Projections!F18*(1+E$5)/($A7-E$5))/(1+$A7)^5 -> 14116.906 | F7: =SUM(Projections!B18/(1+$A7)^1,Projections!C18/(1+$A7)^2,Projections!D18/(1+$A7)^3,Projections!E18/(1+$A7)^4,Projections!F18/(1+$A7)^5)+(Projections!F18*(1+F$5)/($A7-F$5))/(1+$A7)^5 -> 15578.466 | G7: 6.7%: lower-risk case within the model’s sensitivity range.
A8: 0.072 | B8: =SUM(Projections!B18/(1+$A8)^1,Projections!C18/(1+$A8)^2,Projections!D18/(1+$A8)^3,Projections!E18/(1+$A8)^4,Projections!F18/(1+$A8)^5)+(Projections!F18*(1+B$5)/($A8-B$5))/(1+$A8)^5 -> 10269.717 | C8: =SUM(Projections!B18/(1+$A8)^1,Projections!C18/(1+$A8)^2,Projections!D18/(1+$A8)^3,Projections!E18/(1+$A8)^4,Projections!F18/(1+$A8)^5)+(Projections!F18*(1+C$5)/($A8-C$5))/(1+$A8)^5 -> 10951.39 | D8: =SUM(Projections!B18/(1+$A8)^1,Projections!C18/(1+$A8)^2,Projections!D18/(1+$A8)^3,Projections!E18/(1+$A8)^4,Projections!F18/(1+$A8)^5)+(Projections!F18*(1+D$5)/($A8-D$5))/(1+$A8)^5 -> 11752.654 | E8: =SUM(Projections!B18/(1+$A8)^1,Projections!C18/(1+$A8)^2,Projections!D18/(1+$A8)^3,Projections!E18/(1+$A8)^4,Projections!F18/(1+$A8)^5)+(Projections!F18*(1+E$5)/($A8-E$5))/(1+$A8)^5 -> 12708.008 | F8: =SUM(Projections!B18/(1+$A8)^1,Projections!C18/(1+$A8)^2,Projections!D18/(1+$A8)^3,Projections!E18/(1+$A8)^4,Projections!F18/(1+$A8)^5)+(Projections!F18*(1+F$5)/($A8-F$5))/(1+$A8)^5 -> 13866.628 | G8: 7.2%: selected Base-case WACC; the 1.5% column is the primary DCF point.
A9: 0.077 | B9: =SUM(Projections!B18/(1+$A9)^1,Projections!C18/(1+$A9)^2,Projections!D18/(1+$A9)^3,Projections!E18/(1+$A9)^4,Projections!F18/(1+$A9)^5)+(Projections!F18*(1+B$5)/($A9-B$5))/(1+$A9)^5 -> 9515.2759 | C9: =SUM(Projections!B18/(1+$A9)^1,Projections!C18/(1+$A9)^2,Projections!D18/(1+$A9)^3,Projections!E18/(1+$A9)^4,Projections!F18/(1+$A9)^5)+(Projections!F18*(1+C$5)/($A9-C$5))/(1+$A9)^5 -> 10091.447 | D9: =SUM(Projections!B18/(1+$A9)^1,Projections!C18/(1+$A9)^2,Projections!D18/(1+$A9)^3,Projections!E18/(1+$A9)^4,Projections!F18/(1+$A9)^5)+(Projections!F18*(1+D$5)/($A9-D$5))/(1+$A9)^5 -> 10760.549 | E9: =SUM(Projections!B18/(1+$A9)^1,Projections!C18/(1+$A9)^2,Projections!D18/(1+$A9)^3,Projections!E18/(1+$A9)^4,Projections!F18/(1+$A9)^5)+(Projections!F18*(1+E$5)/($A9-E$5))/(1+$A9)^5 -> 11547.037 | F9: =SUM(Projections!B18/(1+$A9)^1,Projections!C18/(1+$A9)^2,Projections!D18/(1+$A9)^3,Projections!E18/(1+$A9)^4,Projections!F18/(1+$A9)^5)+(Projections!F18*(1+F$5)/($A9-F$5))/(1+$A9)^5 -> 12484.773 | G9: 7.7%: execution-risk case used in the lower DCF football-field anchor.
A10: 0.082 | B10: =SUM(Projections!B18/(1+$A10)^1,Projections!C18/(1+$A10)^2,Projections!D18/(1+$A10)^3,Projections!E18/(1+$A10)^4,Projections!F18/(1+$A10)^5)+(Projections!F18*(1+B$5)/($A10-B$5))/(1+$A10)^5 -> 8859.4413 | C10: =SUM(Projections!B18/(1+$A10)^1,Projections!C18/(1+$A10)^2,Projections!D18/(1+$A10)^3,Projections!E18/(1+$A10)^4,Projections!F18/(1+$A10)^5)+(Projections!F18*(1+C$5)/($A10-C$5))/(1+$A10)^5 -> 9351.5821 | D10: =SUM(Projections!B18/(1+$A10)^1,Projections!C18/(1+$A10)^2,Projections!D18/(1+$A10)^3,Projections!E18/(1+$A10)^4,Projections!F18/(1+$A10)^5)+(Projections!F18*(1+D$5)/($A10-D$5))/(1+$A10)^5 -> 9917.1767 | E10: =SUM(Projections!B18/(1+$A10)^1,Projections!C18/(1+$A10)^2,Projections!D18/(1+$A10)^3,Projections!E18/(1+$A10)^4,Projections!F18/(1+$A10)^5)+(Projections!F18*(1+E$5)/($A10-E$5))/(1+$A10)^5 -> 10573.996 | F10: =SUM(Projections!B18/(1+$A10)^1,Projections!C18/(1+$A10)^2,Projections!D18/(1+$A10)^3,Projections!E18/(1+$A10)^4,Projections!F18/(1+$A10)^5)+(Projections!F18*(1+F$5)/($A10-F$5))/(1+$A10)^5 -> 11346.047 | G10: 8.2%: high discount-rate stress case.
A13: INDICATIVE EQUITY VALUE PER SHARE (€)
A14: WACC Terminal growth | B14: 0.005 | C14: 0.01 | D14: 0.015 | E14: 0.02 | F14: 0.025 | G14: Equity interpretation
A15: =A6 -> 0.062 | B15: =MAX((B6-DCF!$B$10-DCF!$B$11)/Assumptions!$B$27,0) -> 17.800433 | C15: =MAX((C6-DCF!$B$10-DCF!$B$11)/Assumptions!$B$27,0) -> 20.178931 | D15: =MAX((D6-DCF!$B$10-DCF!$B$11)/Assumptions!$B$27,0) -> 23.063492 | E15: =MAX((E6-DCF!$B$10-DCF!$B$11)/Assumptions!$B$27,0) -> 26.634854 | F15: =MAX((F6-DCF!$B$10-DCF!$B$11)/Assumptions!$B$27,0) -> 31.171448 | G15: Per-share sensitivity uses FY2025 reported minority interests and the official economic-equivalent share count.
A16: =A7 -> 0.067 | B16: =MAX((B7-DCF!$B$10-DCF!$B$11)/Assumptions!$B$27,0) -> 15.326481 | C16: =MAX((C7-DCF!$B$10-DCF!$B$11)/Assumptions!$B$27,0) -> 17.28422 | D16: =MAX((D7-DCF!$B$10-DCF!$B$11)/Assumptions!$B$27,0) -> 19.618448 | E16: =MAX((E7-DCF!$B$10-DCF!$B$11)/Assumptions!$B$27,0) -> 22.449319 | F16: =MAX((F7-DCF!$B$10-DCF!$B$11)/Assumptions!$B$27,0) -> 25.954208 | G16: Shows how lower discount rates amplify equity value after fixed debt deductions.
A17: =A8 -> 0.072 | B17: =MAX((B8-DCF!$B$10-DCF!$B$11)/Assumptions!$B$27,0) -> 13.223584 | C17: =MAX((C8-DCF!$B$10-DCF!$B$11)/Assumptions!$B$27,0) -> 14.858266 | D17: =MAX((D8-DCF!$B$10-DCF!$B$11)/Assumptions!$B$27,0) -> 16.779735 | E17: =MAX((E8-DCF!$B$10-DCF!$B$11)/Assumptions!$B$27,0) -> 19.070718 | F17: =MAX((F8-DCF!$B$10-DCF!$B$11)/Assumptions!$B$27,0) -> 21.849143 | G17: ="Base-case centre point equals the DCF’s €"&TEXT(DCF!B14,"0.00")&" per-share output." -> Base-case centre point equals the DCF’s €16.78 per-share output.
A18: =A9 -> 0.077 | B18: =MAX((B9-DCF!$B$10-DCF!$B$11)/Assumptions!$B$27,0) -> 11.4144 | C18: =MAX((C9-DCF!$B$10-DCF!$B$11)/Assumptions!$B$27,0) -> 12.796085 | D18: =MAX((D9-DCF!$B$10-DCF!$B$11)/Assumptions!$B$27,0) -> 14.400622 | E18: =MAX((E9-DCF!$B$10-DCF!$B$11)/Assumptions!$B$27,0) -> 16.286657 | F18: =MAX((F9-DCF!$B$10-DCF!$B$11)/Assumptions!$B$27,0) -> 18.535391 | G18: Higher WACC compresses equity value more sharply because debt remains fixed.
A19: =A10 -> 0.082 | B19: =MAX((B10-DCF!$B$10-DCF!$B$11)/Assumptions!$B$27,0) -> 9.8416789 | C19: =MAX((C10-DCF!$B$10-DCF!$B$11)/Assumptions!$B$27,0) -> 11.021855 | D19: =MAX((D10-DCF!$B$10-DCF!$B$11)/Assumptions!$B$27,0) -> 12.378177 | E19: =MAX((E10-DCF!$B$10-DCF!$B$11)/Assumptions!$B$27,0) -> 13.95326 | F19: =MAX((F10-DCF!$B$10-DCF!$B$11)/Assumptions!$B$27,0) -> 15.804674 | G19: Stress case highlights the downside asymmetry created by leverage.
A22: SENSITIVITY DIAGNOSTICS
A23: Diagnostic | B23: Value | C23: Unit / comparison | D23: Interpretation
A24: Base-case enterprise value | B24: =D8 -> 11752.654 | C24: Selected 7.2% WACC / 1.5% terminal growth | D24: The centre point reconciles directly to the DCF enterprise value.
A25: Full-grid EV range | B25: =MAX(B6:F10)-MIN(B6:F10) -> 8894.6465 | C25: Maximum minus minimum across all 25 EV cases | D25: The broad range demonstrates that terminal-value assumptions dominate apparent precision.
A26: Full-grid per-share range | B26: =MAX(B15:F19)-MIN(B15:F19) -> 21.329769 | C26: Maximum minus minimum across all 25 indicative share-price cases | D26: Leverage increases the sensitivity of equity value relative to enterprise value.
A27: +0.5 pp WACC impact at 1.5% g | B27: =D9/D8-1 -> -0.084415408 | C27: EV change from 7.2% to 7.7% WACC | D27: A modest increase in the discount rate causes a meaningful valuation decline.
A28: +0.5 pp terminal growth impact at 7.2% WACC | B28: =E8/D8-1 -> 0.081288347 | C28: EV change from 1.5% to 2.0% terminal growth | D28: A modest increase in terminal growth produces a material valuation uplift.
A30: READING THE SENSITIVITY
A31: ="The selected DCF point is €"&TEXT(D8/1000,"0.0")&"bn of enterprise value at a "&TEXT(A8,"0.0%")&" WACC and "&TEXT(D5,"0.0%")&" terminal growth rate. Across the full matrix, enterprise value ranges from €"&TEXT(MIN(B6:F10)/1000,"0.0")&"bn to €"&TEXT(MAX(B6:F10)/1000,"0.0")&"bn, while indicative equity value per share ranges from €"&TEXT(MIN(B15:F19),"0.00")&" to €"&TEXT(MAX(B15:F19),"0.00")&". At the Base terminal-growth rate, a 0.5 percentage-point increase in WACC reduces EV by "&TEXT(ABS(B27),"0.0%")&"; a 0.5 percentage-point increase in terminal growth raises EV by "&TEXT(B28,"0.0%")&". The model therefore presents valuation ranges rather than false precision." -> The selected DCF point is €11.8bn of enterprise value at a 7.2% WACC and 1.5% terminal growth rate. Across the full matrix, enterprise value ranges from €8.9bn to €17.8bn, while indicative equity value per share ranges from €9.84 to €31.17. At the Base terminal-growth rate, a 0.5 percentage-point increase in WACC reduces EV by 8.4%; a 0.5 percentage-point increase in terminal growth raises EV by 8.1%. The model therefore presents valuation ranges rather than false precision.
A37: MODEL INTEGRITY & RANGE CONTROLS
A38: Control | B38: Result | C38: Expectation | D38: Interpretation
A39: All EV cases valid | B39: =IF(COUNT(B6:F10)=25,"PASS","REVIEW") -> PASS | C39: All 25 enterprise-value cases calculate numerically. | D39: Formula completeness
A40: WACC exceeds terminal growth | B40: =IF(MIN(A6:A10)>MAX(B5:F5),"PASS","REVIEW") -> PASS | C40: Every matrix WACC is greater than every terminal-growth assumption. | D40: Gordon Growth validity
A41: Base case reconciles to DCF | B41: =IF(ABS(D8-DCF!B9)<0.01,"PASS","REVIEW") -> PASS | C41: The 7.2% / 1.5% centre point equals the primary DCF EV. | D41: DCF reconciliation
A42: EV decreases as WACC rises | B42: =IF(AND(D6>D7,D7>D8,D8>D9,D9>D10),"PASS","REVIEW") -> PASS | C42: At 1.5% terminal growth, EV falls monotonically as WACC rises. | D42: Directional sanity check
A43: EV increases as terminal growth rises | B43: =IF(AND(B8<C8,C8<D8,D8<E8,E8<F8),"PASS","REVIEW") -> PASS | C43: At 7.2% WACC, EV rises monotonically as terminal growth increases. | D43: Directional sanity check
A44: Football-field anchors valid | B44: =IF(AND(C9<E7,C9>0),"PASS","REVIEW") -> PASS | C44: The selected lower and upper DCF range anchors are positive and ordered. | D44: Football-field reconciliation

Sheet Comps
A1: Comparable Company Analysis
A2: Five listed satellite and connectivity peers | EV/EBITDA is the primary valuation multiple | Market multiples remain illustrative until refreshed
A4: PEER SET & MULTIPLE INPUTS
A5: Peer | B5: Country / ticker | C5: Business rationale | D5: EV / EBITDA | E5: P/E | F5: Core range? | G5: Input status | H5: Official refresh source
A6: Eutelsat Communications | B6: France / ETL | C6: Closest European listed satellite peer; integrated GEO and OneWeb LEO exposure with video, government, and connectivity operations. | D6: 4.5 | E6: n.m. | F6: Yes | G6: Illustrative | H6: https://www.eutelsat.com/investors/investors
A7: Iridium Communications | B7: US / IRDM | C7: Global LEO connectivity operator with recurring service revenue and a more asset-efficient cash-flow profile; treated as a premium outlier. | D7: 11 | E7: 28 | F7: No — premium outlier | G7: Illustrative | H7: https://investor.iridium.com/
A8: Viasat Inc. | B8: US / VSAT | C8: Global satellite broadband, mobility, and government connectivity operator with high capital intensity. | D8: 6 | E8: n.m. | F8: Yes | G8: Illustrative | H8: https://investors.viasat.com/
A9: Telesat Corporation | B9: Canada / TSAT | C9: GEO operator developing the Lightspeed LEO network; relevant transition and capital-intensity profile. | D9: 5 | E9: n.m. | F9: Yes | G9: Illustrative | H9: https://www.telesat.com/investor-relations/financial-results/
A10: EchoStar Corporation | B10: US / ECHO | C10: Diversified satellite, broadband, wireless, and content-delivery group; earnings comparability is affected by business mix. | D10: 7 | E10: n.m. | F10: Yes | G10: Illustrative | H10: https://ir.echostar.com/financial-information/quarterly-results
A11: PEER SELECTION CRITERIA
A12: 1. Listed satellite or connectivity operator. 2. Similar infrastructure characteristics. 3. Similar capital intensity. 4. Similar revenue model. 5. Relevant to the SES competitive environment. Excluded: companies with materially different business models.
A13: IMPLIED ENTERPRISE VALUE
A14: FY2026E Adjusted EBITDA | B14: =Projections!B8 -> 1195.285 | C14: Selected-case FY2026E EBITDA from Projections.
A15: Peer median EV / EBITDA | B15: =MEDIAN(D6,D8:D10) -> 5.5 | C15: Median of the four core peers; excludes Iridium’s premium multiple.
A16: Peer mean — core set | B16: =AVERAGE(D6,D8:D10) -> 5.625 | C16: Arithmetic mean of the four core peers.
A17: Core low multiple | B17: 5 | C17: Analyst-selected lower bound; above Eutelsat’s distressed/low-end input.
A18: Core high multiple | B18: 7.5 | C18: Analyst-selected upper bound; below Iridium’s premium outlier.
A19: Implied EV — median | B19: =B14*B15 -> 6574.0675 | C19: FY2026E EBITDA × core-peer median.
A20: Implied EV — core mean | B20: =B14*B16 -> 6723.4781 | C20: FY2026E EBITDA × core-peer mean.
A21: Comps EV range — low | B21: =B14*B17 -> 5976.425 | C21: FY2026E EBITDA × 5.0x.
A22: Comps EV range — high | B22: =B14*B18 -> 8964.6375 | C22: FY2026E EBITDA × 7.5x.
A25: COMPS EQUITY VALUE BRIDGE
A26: Metric | B26: Low case | C26: High case | D26: Interpretation
A27: Enterprise value | B27: =B21 -> 5976.425 | C27: =B22 -> 8964.6375 | D27: Core EV/EBITDA valuation range.
A28: Less: Adjusted net debt and minorities | B28: =DCF!B10+DCF!B11 -> 4755.4 | C28: =B28 -> 4755.4 | D28: Fixed valuation bridge using current model net debt and minority interests.
A29: Equity value | B29: =B27-B28 -> 1221.025 | C29: =C27-C28 -> 4209.2375 | D29: Residual value attributable to ordinary equity.
A30: Diluted economic-equivalent shares | B30: =Assumptions!B27 -> 417.00622 | C30: =B30 -> 417.00622 | D30: Source-based economic-equivalent share count from official SES shareholder information.
A31: Indicative value per share | B31: =B29/B30 -> 2.9280738 | C31: =C29/C30 -> 10.093944 | D31: Indicative per-A-share/FDR value using reported minority interests and source-based economic-equivalent shares.
A33: ANALYTICAL INTERPRETATION
A34: ="The core peer set values SES at €"&TEXT(B21/1000,"0.0")&"bn to €"&TEXT(B22/1000,"0.0")&"bn of enterprise value, equivalent to approximately €"&TEXT(B31,"0.00")&" to €"&TEXT(C31,"0.00")&" per share after the current valuation bridge. The core median is "&TEXT(B15,"0.0x")&" and the core mean is "&TEXT(B16,"0.0x")&". This range remains below the €"&TEXT(DCF!B9/1000,"0.0")&_xlfn._LONGTEXT("bn Base-case DCF, indicating that the peer framework prices leverage, integration, and capital-intensity risk more heavily than the intrinsic-value model. EV/EBITDA is emphasized because depreciation and financing structure make P/E less comparable across"," this peer group.") -> The core peer set values SES at €6.0bn to €9.0bn of enterprise value, equivalent to approximately €2.93 to €10.09 per share after the current valuation bridge. The core median is 5.5x and the core mean is 5.6x. This range remains below the €11.8bn Base-case DCF, indicating that the peer framework prices leverage, integration, and capital-intensity risk more heavily than the intrinsic-value model. EV/EBITDA is emphasized because depreciation and financing structure make P/E less comparable across this peer group.
A39: PEER-SET DIAGNOSTICS
A40: Diagnostic | B40: Value | C40: Comparison | D40: Interpretation
A41: Core-peer multiple spread | B41: =MAX(D6,D8:D10)-MIN(D6,D8:D10) -> 2.5 | C41: Highest minus lowest core-peer EV/EBITDA | D41: Shows dispersion even before adding the premium outlier.
A42: DCF premium to comps midpoint | B42: =DCF!B9/AVERAGE(B21,B22)-1 -> 0.57320191 | C42: DCF EV versus midpoint of the core comps range | D42: Quantifies the central valuation tension between intrinsic value and market comparables.
A43: Iridium premium to core median | B43: =D7/B15-1 -> 1 | C43: Iridium EV/EBITDA versus core-peer median | D43: Supports excluding Iridium from the core range while retaining it as a relevant premium reference.
A45: MODEL INTEGRITY & REFRESH CONTROLS
A46: Control | B46: Result | C46: Expectation | D46: Interpretation
A47: Five peers included | B47: =IF(COUNTA(A6:A10)=5,"PASS","REVIEW") -> PASS | C47: The analysis includes exactly five listed peers. | D47: Completeness
A48: Four peers in core statistics | B48: =IF(COUNT(D6,D8:D10)=4,"PASS","REVIEW") -> PASS | C48: Median and mean use four core peers and exclude Iridium. | D48: Outlier methodology
A49: Core range ordered | B49: =IF(B17<B18,"PASS","REVIEW") -> PASS | C49: The selected low multiple is below the selected high multiple. | D49: Range validity
A50: Implied EV formulas complete | B50: =IF(COUNT(B19:B22)=4,"PASS","REVIEW") -> PASS | C50: Median, mean, low, and high implied EV outputs all calculate. | D50: Formula completeness
A51: Equity bridge remains positive | B51: =IF(AND(B29>0,C29>B29),"PASS","REVIEW") -> PASS | C51: Both equity-value endpoints are positive and correctly ordered. | D51: Equity bridge
A52: Official refresh links populated | B52: =IF(COUNTIF(H6:H10,"https://*")=5,"PASS","REVIEW") -> PASS | C52: Each peer has a usable official investor-relations source. | D52: Source refresh

Sheet Football_Field
A1: Valuation Football Field — SES S.A.
A2: ="DCF sensitivity, comparable-company range, and "&TEXT(Assumptions!B9,"0%")&" / "&TEXT(Assumptions!B10,"0%")&" reconciliation | Enterprise value (€m)" -> DCF sensitivity, comparable-company range, and 60% / 40% reconciliation | Enterprise value (€m)
A4: VALUATION RANGE SOURCE TABLE
A5: Method | B5: Low EV | C5: High EV | D5: Chart start | E5: Range width | F5: Weight / methodology | G5: Low vs Base DCF | H5: High vs Base DCF
A6: DCF sensitivity band | B6: =Sensitivity!C9 -> 10091.447 | C6: =Sensitivity!E7 -> 14116.906 | D6: =B6 -> 10091.447 | E6: =C6-B6 -> 4025.4588 | F6: Defined band: 7.7% WACC / 1.0% g (low) to 6.7% WACC / 2.0% g (high). | G6: =B6/DCF!B9-1 -> -0.14134739 | H6: =C6/DCF!B9-1 -> 0.20116748
A7: Comps EV / EBITDA core range | B7: =Comps!B21 -> 5976.425 | C7: =Comps!B22 -> 8964.6375 | D7: =B7 -> 5976.425 | E7: =C7-B7 -> 2988.2125 | F7: 5.0x–7.5x applied to FY2026E Adjusted EBITDA; peer multiples remain illustrative. | G7: =B7/DCF!B9-1 -> -0.49148295 | H7: =C7/DCF!B9-1 -> -0.23722442
A8: Blended fair value range | B8: =Assumptions!B9*B6+Assumptions!B10*B7 -> 8445.4382 | C8: =Assumptions!B9*C6+Assumptions!B10*C7 -> 12055.998 | D8: =B8 -> 8445.4382 | E8: =C8-B8 -> 3610.5603 | F8: =TEXT(Assumptions!B9,"0%")&" DCF / "&TEXT(Assumptions!B10,"0%")&" Comps" -> 60% DCF / 40% Comps | G8: =B8/DCF!B9-1 -> -0.28140161 | H8: =C8/DCF!B9-1 -> 0.02581072
A9: Scope note: This chart reconciles model-derived enterprise-value ranges only. A current-market EV marker is excluded until a validated share price and market capitalization are added; the equity bridge uses official minority-interest and economic-equivalent share data.
A30: BLENDED EQUITY VALUE PER SHARE BRIDGE
A31: Metric | B31: Low case | C31: High case | D31: Interpretation
A32: Blended enterprise value | B32: =B8 -> 8445.4382 | C32: =C8 -> 12055.998 | D32: Weighted reconciliation of DCF and comparable-company enterprise-value ranges.
A33: Less: Adjusted net debt and minorities | B33: =DCF!B10+DCF!B11 -> 4755.4 | C33: =B33 -> 4755.4 | D33: Fixed bridge using modelled adjusted net debt and FY2025 reported minority interests.
A34: Equity value | B34: =B32-B33 -> 3690.0382 | C34: =C32-C33 -> 7300.5985 | D34: Residual value attributable to ordinary equity.
A35: Diluted economic-equivalent shares | B35: =Assumptions!B27 -> 417.00622 | C35: =B35 -> 417.00622 | D35: Source-based economic-equivalent share count from official SES shareholder information.
A36: Indicative value per share | B36: =B34/B35 -> 8.8488805 | C36: =C34/C35 -> 17.507169 | D36: Primary blended fair-value range used in the investment memo.
A37: DCF value per share | B37: =DCF!B14 -> 16.779735 | C37: =DCF!B14 -> 16.779735 | D37: Base-case DCF point estimate for comparison.
A38: Position versus DCF | B38: =B36/B37-1 -> -0.47264481 | C38: =C36/C37-1 -> 0.04335193 | D38: Quantifies the blended range discount or premium to the DCF point estimate.
A40: VALUATION RECONCILIATION
A41: ="The DCF sensitivity band spans €"&TEXT(B6/1000,"0.0")&"bn to €"&TEXT(C6/1000,"0.0")&"bn, while the core comparable-company range is materially lower at €"&TEXT(B7/1000,"0.0")&"bn to €"&TEXT(C7/1000,"0.0")&"bn. Applying the model’s "&TEXT(Assumptions!B9,"0%")&" / "&TEXT(Assumptions!B10,"0%")&" weighting produces a blended enterprise-value range of €"&TEXT(B8/1000,"0.0")&"bn to €"&TEXT(C8/1000,"0.0")&"bn and an indicative equity value of €"&TEXT(B36,"0.00")&" to €"&TEXT(C36,"0.00")&_xlfn._LONGTEXT(" per share. The persistent method gap is decision-relevant: public-market peers apply a materially larger discount for leverage, integration execution, and capital intensity than the DCF. Until a validated current-market reference is added, this tab suppo","rts valuation triangulation rather than a stand-alone buy or sell call.") -> The DCF sensitivity band spans €10.1bn to €14.1bn, while the core comparable-company range is materially lower at €6.0bn to €9.0bn. Applying the model’s 60% / 40% weighting produces a blended enterprise-value range of €8.4bn to €12.1bn and an indicative equity value of €8.85 to €17.51 per share. The persistent method gap is decision-relevant: public-market peers apply a materially larger discount for leverage, integration execution, and capital intensity than the DCF. Until a validated current-market reference is added, this tab supports valuation triangulation rather than a stand-alone buy or sell call.
A47: MODEL INTEGRITY & CHART CONTROLS
A48: Control | B48: Result | C48: Expectation | D48: Interpretation
A49: All valuation ranges ordered | B49: =IF(AND(B6<C6,B7<C7,B8<C8),"PASS","REVIEW") -> PASS | C49: Low is below high for DCF, comps, and blended ranges. | D49: Range validity
A50: Visible ranges positive | B50: =IF(MIN(E6:E8)>0,"PASS","REVIEW") -> PASS | C50: Each floating bar has a positive visible width. | D50: Chart binding
A51: Blend weights sum to 100% | B51: =IF(ABS(Assumptions!B9+Assumptions!B10-1)<0.0001,"PASS","REVIEW") -> PASS | C51: DCF and comps weights total exactly 100%. | D51: Weighting control
A52: Blended range lies between methods | B52: =IF(AND(B8>=MIN(B6,B7),B8<=MAX(B6,B7),C8>=MIN(C6,C7),C8<=MAX(C6,C7)),"PASS","REVIEW") -> PASS | C52: Each blended endpoint lies between the corresponding method endpoints. | D52: Blending logic
A53: Equity bridge balances | B53: =IF(AND(ABS(B34-(B32-B33))<0.01,ABS(C34-(C32-C33))<0.01),"PASS","REVIEW") -> PASS | C53: Equity value equals enterprise value less bridge deductions. | D53: Equity bridge
A54: Per-share range ordered | B54: =IF(AND(B36>0,C36>B36),"PASS","REVIEW") -> PASS | C54: Indicative low and high per-share values are positive and ordered. | D54: Memo output
A55: Live market EV reference included | B55: NOT INCLUDED | C55: Requires validated current market capitalization and net debt. | D55: Data gap — method comparison only.
A56: Core output cells numeric | B56: =IFERROR(IF(AND(ISNUMBER(B6),ISNUMBER(C6),ISNUMBER(B7),ISNUMBER(C7),ISNUMBER(B8),ISNUMBER(C8),ISNUMBER(B36),ISNUMBER(C36)),"PASS","REVIEW"),"REVIEW") -> PASS | C56: DCF, comps, blended EV, and per-share outputs must remain numeric. | D56: Formula integrity

Sheet Charts
A1: SES S.A. — Operating & Valuation Charts
A2: ="Selected "&Assumptions!B5&" case | FY2026E–FY2030E | EUR millions unless stated otherwise" -> Selected Base case | FY2026E–FY2030E | EUR millions unless stated otherwise
A4: OPERATING FORECAST — REVENUE AND ADJUSTED EBITDA
A5: Metric | B5: FY2026E | C5: FY2027E | D5: FY2028E | E5: FY2029E | F5: FY2030E
A6: Revenue | B6: =Projections!B6 -> 2627 | C6: =Projections!C6 -> 2666.405 | D6: =Projections!D6 -> 2719.7331 | E6: =Projections!E6 -> 2787.7264 | F6: =Projections!F6 -> 2857.4196
A7: Adjusted EBITDA | B7: =Projections!B8 -> 1195.285 | C7: =Projections!C8 -> 1253.2103 | D7: =Projections!D8 -> 1305.4719 | E7: =Projections!E8 -> 1352.0473 | F7: =Projections!F8 -> 1400.1356
A27: CASH FLOW CONVERSION — FCFF PROFILE
A28: Metric | B28: FY2026E | C28: FY2027E | D28: FY2028E | E28: FY2029E | F28: FY2030E
A29: FCFF | B29: =Projections!B18 -> 366.34434 | C29: =Projections!C18 -> 513.24563 | D29: =Projections!D18 -> 619.31586 | E29: =Projections!E18 -> 694.51047 | F29: =Projections!F18 -> 747.91386
A46: FY2026E FCFF | C46: FY2030E FCFF | E46: FCFF CAGR | G46: FCFF margin uplift
A47: =Projections!B18 -> 366.34434 | C47: =Projections!F18 -> 747.91386 | E47: =(Projections!F18/Projections!B18)^(1/4)-1 -> 0.19533744 | G47: =(Projections!F18/Projections!F6)-(Projections!B18/Projections!B6) -> 0.122291
A48: VALUATION RANGE SNAPSHOT
A49: Method | B49: Low EV | C49: High EV | D49: ="The model reconciles a DCF range of €"&TEXT(B50/1000,"0.0")&"bn–€"&TEXT(C50/1000,"0.0")&"bn with a lower comps range of €"&TEXT(B51/1000,"0.0")&"bn–€"&TEXT(C51/1000,"0.0")&"bn. The weighted output is €"&TEXT(B52/1000,"0.0")&"bn–€"&TEXT(C52/1000,"0.0")&"bn, equivalent to an indicative €"&TEXT(B53,"0.00")&"–€"&TEXT(C53,"0.00")&" per share. The full football-field visual remains on the Football_Field tab." -> The model reconciles a DCF range of €10.1bn–€14.1bn with a lower comps range of €6.0bn–€9.0bn. The weighted output is €8.4bn–€12.1bn, equivalent to an indicative €8.85–€17.51 per share. The full football-field visual remains on the Football_Field tab.
A50: DCF sensitivity | B50: =Football_Field!B6 -> 10091.447 | C50: =Football_Field!C6 -> 14116.906
A51: Comps EV / EBITDA | B51: =Football_Field!B7 -> 5976.425 | C51: =Football_Field!C7 -> 8964.6375
A52: Blended fair value | B52: =Football_Field!B8 -> 8445.4382 | C52: =Football_Field!C8 -> 12055.998
A53: Indicative blended value per share | B53: =Football_Field!B36 -> 8.8488805 | C53: =Football_Field!C36 -> 17.507169
A56: ANALYST TAKEAWAYS
A57: ="1. Revenue grows at a modest "&TEXT((Projections!F6/Projections!B6)^(1/4)-1,"0.0%")&" CAGR from FY2026E to FY2030E, consistent with a mature infrastructure profile. 2. Adjusted EBITDA grows faster at "&TEXT((Projections!F8/Projections!B8)^(1/4)-1,"0.0%")&" CAGR as the margin recovers from "&TEXT(Projections!B9,"0.0%")&" to "&TEXT(Projections!F9,"0.0%")&". 3. FCFF rises from €"&TEXT(Projections!B18,"#,##0")&"m to €"&TEXT(Projections!F18,"#,##0")&"m as capital intensity normalises. 4. Valuation remains method-sensitive: the comps range is materially below DCF, so the blended range is more defensible than a single point estimate." -> 1. Revenue grows at a modest 2.1% CAGR from FY2026E to FY2030E, consistent with a mature infrastructure profile. 2. Adjusted EBITDA grows faster at 4.0% CAGR as the margin recovers from 45.5% to 49.0%. 3. FCFF rises from €366m to €748m as capital intensity normalises. 4. Valuation remains method-sensitive: the comps range is materially below DCF, so the blended range is more defensible than a single point estimate.

Sheet Sources
A1: SES S.A. — Sources, Provenance & Refresh Register
A2: Official-source hierarchy for historical facts, valuation assumptions, and required market-data refreshes | URLs shown as plain text
A4: PRIMARY DATASET & OFFICIAL SOURCE LINKS
A5: Source | B5: Type / date | C5: Key facts supported | D5: Model location / use | E5: URL | F5: Verification / classification
A6: SES FY2025 Results — official release page | B6: Official results | FY2025 / Mar 2026 | C6: Revenue €2,627m; Adjusted EBITDA €1,196m; leverage 3.9x; FY2026 stable outlook; CapEx and integration context. | D6: Data_Raw; Assumptions; Projections; DCF | E6: https://www.ses.com/news/press-release/full-year-2025-results | F6: Validated 19 Aug 2026 | Source-backed
A7: SES FY2025 Results PDF | B7: Official PDF | FY2025 / Mar 2026 | C7: Downloadable primary results document supporting FY2025 figures, guidance, and transaction-period disclosures. | D7: Data_Raw source table and evidence trail | E7: https://www.ses.com/sites/default/files/2026-03/2603_FY2025%20Press%20Release_Final.pdf | F7: Direct PDF retained; official results page cross-checked | Source-backed
A8: SES Full Year 2024 Results | B8: Official release | 26 Feb 2025 | C8: Revenue €2,001m; Adjusted EBITDA €1,028m; leverage 1.1x; backlog, segment commentary, and Intelsat context. | D8: Data_Raw FY2024 actuals; Historicals | E8: https://www.ses.com/press-release/ses-full-year-2024-results | F8: Validated 19 Aug 2026 | Source-backed
A9: SES Financial Results Hub | B9: Official source hub | current archive | C9: Financial statements, results releases, presentations, and transcripts; preferred starting point for future refreshes. | D9: Refresh control and document discovery | E9: https://www.ses.com/investors/financial-results | F9: Validated 19 Aug 2026 | Official source hub
A10: SES Annual Reports | B10: Official source hub | includes FY2025 | C10: Annual reports, audited statements, responsibility statements, and structured-reporting files. | D10: Equity bridge, minorities, diluted shares, accounting review | E10: https://www.ses.com/investors/annual-reports | F10: Official URL retained; refresh from current archive | Official source hub
A11: SES Completes Acquisition of Intelsat | B11: Official transaction release | 17 Jul 2025 | C11: Confirms acquisition completion on 17 July 2025 and establishes the Intelsat consolidation date. | D11: Data_Raw key facts; historical-period interpretation | E11: https://www.ses.com/press-release/ses-completes-acquisition-intelsat-creating-global-multi-orbit-connectivity | F11: Validated 19 Aug 2026 | Source-backed
A12: PwC Luxembourg Corporate Tax Summary | B12: Professional tax source | 2025+; reviewed 31 Jul 2026 | C12: Luxembourg City combined corporate rate of 23.87% for taxable income above €200,000; simplifying proxy for SES group tax. | D12: Assumptions; WACC tax shield; Projections | E12: https://taxsummaries.pwc.com/luxembourg/corporate/taxes-on-corporate-income | F12: Validated 19 Aug 2026 | External professional source
A13: SES FY2025 Annual Report | B13: Official annual report | FY2025 / Mar 2026 | C13: Non-controlling interests of €91m at 31 December 2025; fully diluted EPS is not materially different from basic EPS. | D13: Assumptions; DCF; Comps; Football_Field; Exec_Summary | E13: https://www.ses.com/sites/default/files/2026-03/SES_AR25_2MAR26_vs21_web-LR.pdf | F13: Validated 1 Sep 2026 | Source-backed
A14: SES Shareholders | B14: Official shareholder information | 30 Jun 2026 | C14: 521.258m actual shares and 417.006m economic-equivalent shares; B-shares carry 40% of A-share economic rights. | D14: Assumptions and all per-share valuation outputs | E14: https://www.ses.com/investors/shareholder-information/shareholders | F14: Validated 1 Sep 2026 | Source-backed
A15: SOURCE-USE NOTES & ACCURACY CONTROLS
A16: Control | B16: Status | C16: Interpretation
A17: Official sources prioritized | B17: PASS | C17: SES releases, PDFs, and investor-relations hubs are the primary evidence base; third-party aggregators are not treated as authoritative.
A18: FY2025 actuals reconcile | B18: PASS | C18: Revenue €2,627m and Adjusted EBITDA €1,196m reconcile to Data_Raw, Historicals, Assumptions, and valuation outputs.
A19: FY2024 actuals reconcile | B19: PASS | C19: Revenue €2,001m, Adjusted EBITDA €1,028m, and leverage 1.1x reconcile to the model.
A20: Intelsat completion date consistent | B20: PASS | C20: 17 July 2025 is used consistently to explain FY2025 as a transition and partial-consolidation year.
A21: Tax proxy applied correctly | B21: PASS | C21: 23.87% is the Luxembourg City 2025+ combined rate; the workbook explicitly notes that SES operates across multiple jurisdictions.
A22: Live market reference included | B22: PASS | C22: Minority interests and economic-equivalent shares are source-based; no validated current share price, market capitalization, or market enterprise value is included.
A25: ILLUSTRATIVE INPUTS — REFRESH BEFORE LIVE USE
A26: Input | B26: Current treatment | C26: Required refresh source | D26: Affected outputs | E26: Priority / status | F26: Action and reason
A27: Peer betas and debt / equity | B27: Illustrative five-peer inputs | C27: Bloomberg, Capital IQ, FactSet, Refinitiv, or current filings | D27: WACC beta and cost of equity | E27: High / OPEN | F27: Refresh all peers on one date. Market-sensitive and capital-structure dependent.
A28: Pre-tax cost of debt / credit spread | B28: Illustrative 4.3% | C28: Observable SES EUR bond yields, debt notes, and market credit data | D28: WACC and DCF | E28: High / OPEN | F28: Rebuild from current debt mix and yields. Direct valuation impact.
A29: Peer EV / EBITDA and P / E | B29: Illustrative multiples | C29: Bloomberg, Capital IQ, FactSet, Refinitiv, or latest filings | D29: Comps and blended valuation | E29: High / OPEN | F29: Refresh price, EV, and LTM / NTM metrics consistently.
A30: Minority interests | B30: Reported €91m | C30: SES FY2025 Annual Report / consolidated statement of financial position | D30: All equity bridges | E30: Closed / SOURCE-BACKED | F30: FY2025 non-controlling interests at 31 December 2025; direct equity-value deduction.
A31: Diluted economic-equivalent shares | B31: 417.006m economic-equivalent | C31: SES shareholder information and FY2025 diluted-EPS disclosure | D31: All per-share outputs | E31: Closed / SOURCE-BACKED | F31: Official 30 June 2026 capital structure; B-shares weighted at 40% of A-share economic rights.
A32: Current share price and market EV | B32: Not included | C32: Euronext / Luxembourg Stock Exchange and validated market-data provider | D32: Recommendation and market reference | E32: Critical / OPEN | F32: Observation date is established; add validated price, market capitalization, and market EV before an unconditional call.
A33: FY2027–FY2030 operating drivers | B33: Analyst judgement by scenario | C33: Management updates, consensus, filings, and sector research | D33: Projections, DCF, Sensitivity | E33: Medium / OPEN | F33: Refresh after each results cycle. Forecast assumptions drive cash flow.
A36: REFRESH PROTOCOL
A37: Step | B37: Required action | C37: Evidence retained | D37: Workbook update
A38: 1 | B38: Maintain one market-data observation date for price, betas, yields, and peer multiples. | C38: Provider export or dated report | D38: Update WACC and Comps inputs
A39: 2 | B39: Revalidate diluted economic-equivalent shares, minorities, and adjusted net debt against each latest filing. | C39: Annual-report note references | D39: Update Assumptions and all equity bridges
A40: 3 | B40: Refresh management guidance and forecast drivers after each results release. | C40: Official release, presentation, and transcript | D40: Update Assumptions scenario library
A41: 4 | B41: Re-run controls and compare the validated market price with the fair-value range. | C41: PASS controls and dated review note | D41: Update Football_Field and Exec_Summary recommendation
A43: MARKET INPUT, LISTING & DEBT-REFRESH SOURCES
A44: Source | B44: Input supported | C44: Observation / use | D44: URL | E44: Status | F44: Classification
A45: Deutsche Finanzagentur bond factsheet | B45: 2.99% German Bund reference proxy | C45: 18 Aug 2026; Aug-2032 maturity, ISIN DE0001102606 | D45: https://www.deutsche-finanzagentur.de/en/federal-securities/factsheet/isin/DE0001102606 | E45: Validated 19 Aug 2026 | F45: Official sovereign source
A46: Damodaran historical implied ERP | B46: 4.23% annual implied ERP | C46: January 2026 annual dataset used in WACC | D46: https://pages.stern.nyu.edu/~adamodar/New_Home_Page/datafile/histimpl.html | E46: Validated 19 Aug 2026 | F46: Academic / market-data source
A47: SES Investors | B47: Listing venues and ticker SESG | C47: Euronext Paris and Luxembourg Stock Exchange | D47: https://www.ses.com/investors | E47: Validated 19 Aug 2026 | F47: Official company source
A48: SES Debtholder Information | B48: Debt-cost refresh reference | C48: Use for current debt mix and observable bond information | D48: https://www.ses.com/investors/debtholder-information | E48: Official refresh reference | F48: Official company source
A50: Source conclusion: the historical, guidance, minority-interest, and economic-share inputs are official and traceable; market-sensitive valuation inputs and the current market reference still require refresh before live investment use.
